{
"meta":{"test_sets":[],"test_metrics":[],"learn_metrics":[{"best_value":"Min","name":"RMSE"}],"launch_mode":"Train","parameters":"","iteration_count":1000,"learn_sets":["learn"],"name":"experiment"},
"iterations":[
{"learn":[14.61268541],"iteration":0,"passed_time":0.08139883086,"remaining_time":81.31743203},
{"learn":[14.23196558],"iteration":1,"passed_time":0.08200908697,"remaining_time":40.9225344},
{"learn":[13.86674177],"iteration":2,"passed_time":0.08252308933,"remaining_time":27.42517335},
{"learn":[13.49946468],"iteration":3,"passed_time":0.08300376067,"remaining_time":20.66793641},
{"learn":[13.16661202],"iteration":4,"passed_time":0.08348577234,"remaining_time":16.6136687},
{"learn":[12.85632158],"iteration":5,"passed_time":0.08394712017,"remaining_time":13.90723957},
{"learn":[12.56784336],"iteration":6,"passed_time":0.08441345465,"remaining_time":11.97465149},
{"learn":[12.31617801],"iteration":7,"passed_time":0.08488024912,"remaining_time":10.52515089},
{"learn":[12.01509946],"iteration":8,"passed_time":0.08534246886,"remaining_time":9.397154071},
{"learn":[11.71512571],"iteration":9,"passed_time":0.08579201662,"remaining_time":8.493409645},
{"learn":[11.43264457],"iteration":10,"passed_time":0.08624781923,"remaining_time":7.75446302},
{"learn":[11.17973129],"iteration":11,"passed_time":0.08674812984,"remaining_time":7.14226269},
{"learn":[10.93746433],"iteration":12,"passed_time":0.08721677192,"remaining_time":6.621765683},
{"learn":[10.69387075],"iteration":13,"passed_time":0.0876834562,"remaining_time":6.175420558},
{"learn":[10.4615922],"iteration":14,"passed_time":0.08821470167,"remaining_time":5.79276541},
{"learn":[10.2299235],"iteration":15,"passed_time":0.08877835775,"remaining_time":5.459869002},
{"learn":[10.01419731],"iteration":16,"passed_time":0.08928509992,"remaining_time":5.162779601},
{"learn":[9.795856918],"iteration":17,"passed_time":0.08978613939,"remaining_time":4.898332716},
{"learn":[9.60040151],"iteration":18,"passed_time":0.09028733514,"remaining_time":4.661677672},
{"learn":[9.418664989],"iteration":19,"passed_time":0.09075705509,"remaining_time":4.447095699},
{"learn":[9.249278645],"iteration":20,"passed_time":0.09127137479,"remaining_time":4.254984568},
{"learn":[9.090113396],"iteration":21,"passed_time":0.09175007953,"remaining_time":4.078708081},
{"learn":[8.909548708],"iteration":22,"passed_time":0.09222519403,"remaining_time":3.917565851},
{"learn":[8.740140208],"iteration":23,"passed_time":0.0927151002,"remaining_time":3.770414075},
{"learn":[8.59377682],"iteration":24,"passed_time":0.09317962353,"remaining_time":3.634005318},
{"learn":[8.453885414],"iteration":25,"passed_time":0.0936513133,"remaining_time":3.508322275},
{"learn":[8.317732234],"iteration":26,"passed_time":0.09411482047,"remaining_time":3.391619271},
{"learn":[8.180896085],"iteration":27,"passed_time":0.09460570313,"remaining_time":3.284169409},
{"learn":[8.053220863],"iteration":28,"passed_time":0.09519936566,"remaining_time":3.187537381},
{"learn":[7.924234474],"iteration":29,"passed_time":0.09579419541,"remaining_time":3.097345652},
{"learn":[7.818879511],"iteration":30,"passed_time":0.09627594743,"remaining_time":3.009399776},
{"learn":[7.719346395],"iteration":31,"passed_time":0.09676336007,"remaining_time":2.927091642},
{"learn":[7.624163594],"iteration":32,"passed_time":0.0972622426,"remaining_time":2.850078442},
{"learn":[7.524952543],"iteration":33,"passed_time":0.09773197698,"remaining_time":2.776737934},
{"learn":[7.424464745],"iteration":34,"passed_time":0.09822055283,"remaining_time":2.708080957},
{"learn":[7.327482321],"iteration":35,"passed_time":0.09870122538,"remaining_time":2.64299948},
{"learn":[7.238666841],"iteration":36,"passed_time":0.09916615462,"remaining_time":2.581000186},
{"learn":[7.158842395],"iteration":37,"passed_time":0.09965482023,"remaining_time":2.522840449},
{"learn":[7.074348246],"iteration":38,"passed_time":0.1001437347,"remaining_time":2.467644334},
{"learn":[6.992269093],"iteration":39,"passed_time":0.1006190796,"remaining_time":2.41485791},
{"learn":[6.925219745],"iteration":40,"passed_time":0.1010835104,"remaining_time":2.364367962},
{"learn":[6.86013671],"iteration":41,"passed_time":0.1015729942,"remaining_time":2.316831629},
{"learn":[6.786739622],"iteration":42,"passed_time":0.1021052903,"remaining_time":2.272436344},
{"learn":[6.73057926],"iteration":43,"passed_time":0.102643858,"remaining_time":2.230171097},
{"learn":[6.666356486],"iteration":44,"passed_time":0.1031388386,"remaining_time":2.188835353},
{"learn":[6.606182832],"iteration":45,"passed_time":0.1036132491,"remaining_time":2.148848688},
{"learn":[6.547854615],"iteration":46,"passed_time":0.1040762979,"remaining_time":2.110313018},
{"learn":[6.49240675],"iteration":47,"passed_time":0.1045739643,"remaining_time":2.074050292},
{"learn":[6.431317261],"iteration":48,"passed_time":0.1050535373,"remaining_time":2.038896204},
{"learn":[6.377586395],"iteration":49,"passed_time":0.1055322934,"remaining_time":2.005113574},
{"learn":[6.327558015],"iteration":50,"passed_time":0.1059939401,"remaining_time":1.972318611},
{"learn":[6.282040317],"iteration":51,"passed_time":0.106470687,"remaining_time":1.941042525},
{"learn":[6.237655841],"iteration":52,"passed_time":0.1069356035,"remaining_time":1.910717292},
{"learn":[6.192792003],"iteration":53,"passed_time":0.1073911027,"remaining_time":1.881333022},
{"learn":[6.150579347],"iteration":54,"passed_time":0.1078736285,"remaining_time":1.853465071},
{"learn":[6.115693845],"iteration":55,"passed_time":0.1083445858,"remaining_time":1.82638016},
{"learn":[6.078780782],"iteration":56,"passed_time":0.1088223561,"remaining_time":1.800341786},
{"learn":[6.045146957],"iteration":57,"passed_time":0.1094671169,"remaining_time":1.777896967},
{"learn":[6.008080327],"iteration":58,"passed_time":0.1100960117,"remaining_time":1.755938085},
{"learn":[5.977575734],"iteration":59,"passed_time":0.1105828301,"remaining_time":1.732464338},
{"learn":[5.948036502],"iteration":60,"passed_time":0.1110455343,"remaining_time":1.709373061},
{"learn":[5.914888282],"iteration":61,"passed_time":0.1115187419,"remaining_time":1.687170644},
{"learn":[5.884957796],"iteration":62,"passed_time":0.1119796005,"remaining_time":1.665474375},
{"learn":[5.849539885],"iteration":63,"passed_time":0.1124323919,"remaining_time":1.644323731},
{"learn":[5.821387627],"iteration":64,"passed_time":0.112923329,"remaining_time":1.624358656},
{"learn":[5.797012279],"iteration":65,"passed_time":0.1133796032,"remaining_time":1.604493173},
{"learn":[5.768685095],"iteration":66,"passed_time":0.1138527571,"remaining_time":1.585442126},
{"learn":[5.755484587],"iteration":67,"passed_time":0.1140979368,"remaining_time":1.563812899},
{"learn":[5.731887055],"iteration":68,"passed_time":0.1145566493,"remaining_time":1.545684645},
{"learn":[5.707148487],"iteration":69,"passed_time":0.1150297972,"remaining_time":1.528253019},
{"learn":[5.685365039],"iteration":70,"passed_time":0.1154988227,"remaining_time":1.511245159},
{"learn":[5.663541834],"iteration":71,"passed_time":0.1159946387,"remaining_time":1.49504201},
{"learn":[5.638108797],"iteration":72,"passed_time":0.1165476315,"remaining_time":1.479995266},
{"learn":[5.619204893],"iteration":73,"passed_time":0.1171201161,"remaining_time":1.465584156},
{"learn":[5.598472793],"iteration":74,"passed_time":0.1176163845,"remaining_time":1.450602076},
{"learn":[5.577007075],"iteration":75,"passed_time":0.1180939629,"remaining_time":1.43577397},
{"learn":[5.562637084],"iteration":76,"passed_time":0.1185792318,"remaining_time":1.421410792},
{"learn":[5.54729991],"iteration":77,"passed_time":0.1190505333,"remaining_time":1.407238355},
{"learn":[5.530737623],"iteration":78,"passed_time":0.1195243187,"remaining_time":1.393441741},
{"learn":[5.513704873],"iteration":79,"passed_time":0.1199950544,"remaining_time":1.379943126},
{"learn":[5.501575529],"iteration":80,"passed_time":0.1204538875,"remaining_time":1.366631143},
{"learn":[5.484080734],"iteration":81,"passed_time":0.120911008,"remaining_time":1.353613479},
{"learn":[5.472178894],"iteration":82,"passed_time":0.1213930545,"remaining_time":1.341173867},
{"learn":[5.458923342],"iteration":83,"passed_time":0.1218730939,"remaining_time":1.328997072},
{"learn":[5.451382371],"iteration":84,"passed_time":0.1222025638,"remaining_time":1.315474658},
{"learn":[5.441410748],"iteration":85,"passed_time":0.1227048743,"remaining_time":1.30409599},
{"learn":[5.434047468],"iteration":86,"passed_time":0.1230733679,"remaining_time":1.291563044},
{"learn":[5.422107497],"iteration":87,"passed_time":0.1237468649,"remaining_time":1.282467509},
{"learn":[5.40731265],"iteration":88,"passed_time":0.1243675607,"remaining_time":1.273020762},
{"learn":[5.396360181],"iteration":89,"passed_time":0.1248735572,"remaining_time":1.262610411},
{"learn":[5.383793239],"iteration":90,"passed_time":0.1253473334,"remaining_time":1.25209589},
{"learn":[5.369605034],"iteration":91,"passed_time":0.1258082548,"remaining_time":1.241672776},
{"learn":[5.357467333],"iteration":92,"passed_time":0.1262905975,"remaining_time":1.231672816},
{"learn":[5.341109968],"iteration":93,"passed_time":0.1267701549,"remaining_time":1.221848514},
{"learn":[5.330529276],"iteration":94,"passed_time":0.1272652036,"remaining_time":1.212368518},
{"learn":[5.319862075],"iteration":95,"passed_time":0.1277551598,"remaining_time":1.203027755},
{"learn":[5.313052243],"iteration":96,"passed_time":0.1282249527,"remaining_time":1.193681776},
{"learn":[5.299677207],"iteration":97,"passed_time":0.1286775762,"remaining_time":1.184358916},
{"learn":[5.287546698],"iteration":98,"passed_time":0.1291542646,"remaining_time":1.175434267},
{"learn":[5.279803754],"iteration":99,"passed_time":0.1296511369,"remaining_time":1.166860232},
{"learn":[5.272254612],"iteration":100,"passed_time":0.1301965065,"remaining_time":1.158877815},
{"learn":[5.268813888],"iteration":101,"passed_time":0.1304999672,"remaining_time":1.148911476},
{"learn":[5.258113767],"iteration":102,"passed_time":0.1310153944,"remaining_time":1.140978726},
{"learn":[5.251018576],"iteration":103,"passed_time":0.1315104067,"remaining_time":1.133012734},
{"learn":[5.24171237],"iteration":104,"passed_time":0.1320029955,"remaining_time":1.12516839},
{"learn":[5.233984943],"iteration":105,"passed_time":0.1324652621,"remaining_time":1.117207022},
{"learn":[5.226240449],"iteration":106,"passed_time":0.1329162131,"remaining_time":1.109291386},
{"learn":[5.220541644],"iteration":107,"passed_time":0.1333873174,"remaining_time":1.101680437},
{"learn":[5.211712096],"iteration":108,"passed_time":0.133853018,"remaining_time":1.094156322},
{"learn":[5.203388597],"iteration":109,"passed_time":0.1343302819,"remaining_time":1.086854099},
{"learn":[5.196026544],"iteration":110,"passed_time":0.1347823227,"remaining_time":1.079472837},
{"learn":[5.188716772],"iteration":111,"passed_time":0.1352544849,"remaining_time":1.072374845},
{"learn":[5.182163132],"iteration":112,"passed_time":0.1357104759,"remaining_time":1.065267187},
{"learn":[5.17764747],"iteration":113,"passed_time":0.136162919,"remaining_time":1.058248652},
{"learn":[5.170548056],"iteration":114,"passed_time":0.1366111012,"remaining_time":1.051311518},
{"learn":[5.165901827],"iteration":115,"passed_time":0.1370129915,"remaining_time":1.044133487},
{"learn":[5.160333668],"iteration":116,"passed_time":0.1375933702,"remaining_time":1.038418341},
{"learn":[5.148953243],"iteration":117,"passed_time":0.1380715232,"remaining_time":1.032026131},
{"learn":[5.144729126],"iteration":118,"passed_time":0.1385162786,"remaining_time":1.025486063},
{"learn":[5.139939946],"iteration":119,"passed_time":0.1391827691,"remaining_time":1.02067364},
{"learn":[5.132898872],"iteration":120,"passed_time":0.139707,"remaining_time":1.014896306},
{"learn":[5.129073077],"iteration":121,"passed_time":0.1402154026,"remaining_time":1.009091176},
{"learn":[5.127123916],"iteration":122,"passed_time":0.14048275,"remaining_time":1.001653429},
{"learn":[5.121282057],"iteration":123,"passed_time":0.1409791478,"remaining_time":0.9959494634},
{"learn":[5.114489821],"iteration":124,"passed_time":0.1414423376,"remaining_time":0.9900963633},
{"learn":[5.107777291],"iteration":125,"passed_time":0.141904932,"remaining_time":0.9843246871},
{"learn":[5.103518754],"iteration":126,"passed_time":0.1424057699,"remaining_time":0.9788995051},
{"learn":[5.101133351],"iteration":127,"passed_time":0.1427060896,"remaining_time":0.9721852357},
{"learn":[5.096462705],"iteration":128,"passed_time":0.1431839886,"remaining_time":0.9667694113},
{"learn":[5.08562082],"iteration":129,"passed_time":0.1436622421,"remaining_time":0.9614319281},
{"learn":[5.080483682],"iteration":130,"passed_time":0.1441920074,"remaining_time":0.9565103394},
{"learn":[5.07437499],"iteration":131,"passed_time":0.1448454881,"remaining_time":0.9524688158},
{"learn":[5.070683732],"iteration":132,"passed_time":0.1453729731,"remaining_time":0.9476568996},
{"learn":[5.06432037],"iteration":133,"passed_time":0.1458536536,"remaining_time":0.9426064481},
{"learn":[5.057436484],"iteration":134,"passed_time":0.1463168499,"remaining_time":0.9375116676},
{"learn":[5.053254656],"iteration":135,"passed_time":0.1467837802,"remaining_time":0.9325087211},
{"learn":[5.04801663],"iteration":136,"passed_time":0.1472658636,"remaining_time":0.9276674471},
{"learn":[5.045680836],"iteration":137,"passed_time":0.1476406468,"remaining_time":0.9222191129},
{"learn":[5.041857933],"iteration":138,"passed_time":0.1481175769,"remaining_time":0.9174765015},
{"learn":[5.035264888],"iteration":139,"passed_time":0.1485744874,"remaining_time":0.9126718513},
{"learn":[5.028771948],"iteration":140,"passed_time":0.1490371367,"remaining_time":0.9079638329},
{"learn":[5.024912247],"iteration":141,"passed_time":0.1494914002,"remaining_time":0.9032649395},
{"learn":[5.02239068],"iteration":142,"passed_time":0.1499502045,"remaining_time":0.898652624},
{"learn":[5.017110572],"iteration":143,"passed_time":0.1504133815,"remaining_time":0.8941239898},
{"learn":[5.010707886],"iteration":144,"passed_time":0.1508897313,"remaining_time":0.8897291053},
{"learn":[5.004389868],"iteration":145,"passed_time":0.1514546304,"remaining_time":0.8859058515},
{"learn":[4.997628683],"iteration":146,"passed_time":0.1519586963,"remaining_time":0.8817739315},
{"learn":[4.991497851],"iteration":147,"passed_time":0.1524350473,"remaining_time":0.8775314887},
{"learn":[4.988345253],"iteration":148,"passed_time":0.1530270233,"remaining_time":0.8739999789},
{"learn":[4.98460423],"iteration":149,"passed_time":0.1536306471,"remaining_time":0.8705736672},
{"learn":[4.982441783],"iteration":150,"passed_time":0.1541247987,"remaining_time":0.8665692323},
{"learn":[4.977461771],"iteration":151,"passed_time":0.1545820774,"remaining_time":0.8624052741},
{"learn":[4.973601586],"iteration":152,"passed_time":0.1550551873,"remaining_time":0.8583774093},
{"learn":[4.968328804],"iteration":153,"passed_time":0.1555108076,"remaining_time":0.8542996311},
{"learn":[4.9640736],"iteration":154,"passed_time":0.1559855258,"remaining_time":0.8503727051},
{"learn":[4.960865882],"iteration":155,"passed_time":0.156443089,"remaining_time":0.8463972253},
{"learn":[4.957014156],"iteration":156,"passed_time":0.1569043924,"remaining_time":0.842486642},
{"learn":[4.952244852],"iteration":157,"passed_time":0.1573693906,"remaining_time":0.8386394104},
{"learn":[4.949695675],"iteration":158,"passed_time":0.1578236313,"remaining_time":0.8347778232},
{"learn":[4.946584698],"iteration":159,"passed_time":0.1584155127,"remaining_time":0.8316814416},
{"learn":[4.940192834],"iteration":160,"passed_time":0.158940232,"remaining_time":0.8282661782},
{"learn":[4.936727994],"iteration":161,"passed_time":0.1594343824,"remaining_time":0.8247284717},
{"learn":[4.932342063],"iteration":162,"passed_time":0.1599164654,"remaining_time":0.8211661442},
{"learn":[4.925830838],"iteration":163,"passed_time":0.1603879223,"remaining_time":0.8175872138},
{"learn":[4.922571773],"iteration":164,"passed_time":0.1608816018,"remaining_time":0.8141584092},
{"learn":[4.918395814],"iteration":165,"passed_time":0.1613411894,"remaining_time":0.8105936865},
{"learn":[4.911142452],"iteration":166,"passed_time":0.1617983464,"remaining_time":0.807054027},
{"learn":[4.908276131],"iteration":167,"passed_time":0.1622494188,"remaining_time":0.803520931},
{"learn":[4.904584645],"iteration":168,"passed_time":0.1627191139,"remaining_time":0.8001158794},
{"learn":[4.89795517],"iteration":169,"passed_time":0.1631792772,"remaining_time":0.7966988242},
{"learn":[4.895556491],"iteration":170,"passed_time":0.1636553238,"remaining_time":0.7933933532},
{"learn":[4.890591233],"iteration":171,"passed_time":0.1641148753,"remaining_time":0.7900413763},
{"learn":[4.884629277],"iteration":172,"passed_time":0.1645787675,"remaining_time":0.7867435881},
{"learn":[4.880550786],"iteration":173,"passed_time":0.1652364178,"remaining_time":0.7843981674},
{"learn":[4.876384842],"iteration":174,"passed_time":0.1657778947,"remaining_time":0.7815243605},
{"learn":[4.872638238],"iteration":175,"passed_time":0.166278416,"remaining_time":0.7784853114},
{"learn":[4.869137118],"iteration":176,"passed_time":0.1667426296,"remaining_time":0.7753061253},
{"learn":[4.863587157],"iteration":177,"passed_time":0.1672043549,"remaining_time":0.7721459536},
{"learn":[4.858028614],"iteration":178,"passed_time":0.1677460441,"remaining_time":0.7693826938},
{"learn":[4.853838176],"iteration":179,"passed_time":0.1683020108,"remaining_time":0.7667091605},
{"learn":[4.853462329],"iteration":180,"passed_time":0.1685454162,"remaining_time":0.7626447287},
{"learn":[4.851573196],"iteration":181,"passed_time":0.1690145828,"remaining_time":0.7596369711},
{"learn":[4.848442087],"iteration":182,"passed_time":0.1694768406,"remaining_time":0.7566261136},
{"learn":[4.845547104],"iteration":183,"passed_time":0.1699447651,"remaining_time":0.7536680885},
{"learn":[4.839868817],"iteration":184,"passed_time":0.1704143644,"remaining_time":0.7507443621},
{"learn":[4.836336958],"iteration":185,"passed_time":0.1709167077,"remaining_time":0.7479903231},
{"learn":[4.831124789],"iteration":186,"passed_time":0.1714038844,"remaining_time":0.7451944277},
{"learn":[4.827407333],"iteration":187,"passed_time":0.1718849464,"remaining_time":0.7423966833},
{"learn":[4.824088918],"iteration":188,"passed_time":0.172436229,"remaining_time":0.739924771},
{"learn":[4.820934539],"iteration":189,"passed_time":0.1729788931,"remaining_time":0.7374363337},
{"learn":[4.816975227],"iteration":190,"passed_time":0.1734986302,"remaining_time":0.7348711614},
{"learn":[4.812340486],"iteration":191,"passed_time":0.1740222047,"remaining_time":0.732343445},
{"learn":[4.806402747],"iteration":192,"passed_time":0.1745155645,"remaining_time":0.7297101583},
{"learn":[4.801521788],"iteration":193,"passed_time":0.1750069152,"remaining_time":0.7270905857},
{"learn":[4.797601172],"iteration":194,"passed_time":0.175461678,"remaining_time":0.7243417988},
{"learn":[4.792694629],"iteration":195,"passed_time":0.1759220321,"remaining_time":0.7216393561},
{"learn":[4.789794613],"iteration":196,"passed_time":0.1764022106,"remaining_time":0.7190404827},
{"learn":[4.785367055],"iteration":197,"passed_time":0.1768543596,"remaining_time":0.7163494769},
{"learn":[4.780376856],"iteration":198,"passed_time":0.1773226006,"remaining_time":0.7137457442},
{"learn":[4.776691261],"iteration":199,"passed_time":0.1778008682,"remaining_time":0.7112034728},
{"learn":[4.773470753],"iteration":200,"passed_time":0.1782764215,"remaining_time":0.708670949},
{"learn":[4.77207327],"iteration":201,"passed_time":0.1788325305,"remaining_time":0.7064770263},
{"learn":[4.767347177],"iteration":202,"passed_time":0.1794279597,"remaining_time":0.704453615},
{"learn":[4.763983068],"iteration":203,"passed_time":0.1799777012,"remaining_time":0.7022659322},
{"learn":[4.761588849],"iteration":204,"passed_time":0.1804580003,"remaining_time":0.699824928},
{"learn":[4.758558086],"iteration":205,"passed_time":0.1809227332,"remaining_time":0.697342962},
{"learn":[4.753678804],"iteration":206,"passed_time":0.1813850723,"remaining_time":0.6948713158},
{"learn":[4.746510889],"iteration":207,"passed_time":0.1818503907,"remaining_time":0.6924303337},
{"learn":[4.744840601],"iteration":208,"passed_time":0.1823751244,"remaining_time":0.6902331265},
{"learn":[4.741702222],"iteration":209,"passed_time":0.1829002749,"remaining_time":0.6880534152},
{"learn":[4.739352853],"iteration":210,"passed_time":0.1833777716,"remaining_time":0.6857111932},
{"learn":[4.735539287],"iteration":211,"passed_time":0.1838426812,"remaining_time":0.6833397772},
{"learn":[4.730726751],"iteration":212,"passed_time":0.1842990984,"remaining_time":0.6809548849},
{"learn":[4.726416092],"iteration":213,"passed_time":0.1847936915,"remaining_time":0.6787282315},
{"learn":[4.721293082],"iteration":214,"passed_time":0.1852490678,"remaining_time":0.6763745034},
{"learn":[4.718443695],"iteration":215,"passed_time":0.185807157,"remaining_time":0.6744111626},
{"learn":[4.711627962],"iteration":216,"passed_time":0.1863497622,"remaining_time":0.6724049024},
{"learn":[4.709790764],"iteration":217,"passed_time":0.1868408108,"remaining_time":0.6702271285},
{"learn":[4.706913073],"iteration":218,"passed_time":0.1873084819,"remaining_time":0.66798139},
{"learn":[4.703846389],"iteration":219,"passed_time":0.1877802358,"remaining_time":0.6657662907},
{"learn":[4.701001135],"iteration":220,"passed_time":0.1882445945,"remaining_time":0.6635409009},
{"learn":[4.700380864],"iteration":221,"passed_time":0.1886801456,"remaining_time":0.66123042},
{"learn":[4.695837486],"iteration":222,"passed_time":0.189139548,"remaining_time":0.6590198601},
{"learn":[4.691242996],"iteration":223,"passed_time":0.189598,"remaining_time":0.6568216429},
{"learn":[4.690284609],"iteration":224,"passed_time":0.1900514678,"remaining_time":0.6546217223},
{"learn":[4.68827119],"iteration":225,"passed_time":0.1905127731,"remaining_time":0.6524640991},
{"learn":[4.686922425],"iteration":226,"passed_time":0.1909536951,"remaining_time":0.6502520103},
{"learn":[4.686085874],"iteration":227,"passed_time":0.1914057757,"remaining_time":0.6480932404},
{"learn":[4.683230741],"iteration":228,"passed_time":0.1918697877,"remaining_time":0.6459895473},
{"learn":[4.6773487],"iteration":229,"passed_time":0.1923427429,"remaining_time":0.6439300523},
{"learn":[4.671462906],"iteration":230,"passed_time":0.1928719877,"remaining_time":0.6420716819},
{"learn":[4.664799601],"iteration":231,"passed_time":0.1934507492,"remaining_time":0.6403886869},
{"learn":[4.660979386],"iteration":232,"passed_time":0.1940068017,"remaining_time":0.6386404158},
{"learn":[4.656281279],"iteration":233,"passed_time":0.1944750226,"remaining_time":0.6366148176},
{"learn":[4.651997094],"iteration":234,"passed_time":0.1949371542,"remaining_time":0.6345826509},
{"learn":[4.650151977],"iteration":235,"passed_time":0.1954089918,"remaining_time":0.6325952108},
{"learn":[4.648478046],"iteration":236,"passed_time":0.1958731461,"remaining_time":0.6305958248},
{"learn":[4.646364602],"iteration":237,"passed_time":0.1963305271,"remaining_time":0.6285876539},
{"learn":[4.642635873],"iteration":238,"passed_time":0.1968584179,"remaining_time":0.6268169708},
{"learn":[4.640860821],"iteration":239,"passed_time":0.1973553314,"remaining_time":0.6249585495},
{"learn":[4.639446822],"iteration":240,"passed_time":0.1978266646,"remaining_time":0.6230308648},
{"learn":[4.637120072],"iteration":241,"passed_time":0.1982898572,"remaining_time":0.621089718},
{"learn":[4.633769267],"iteration":242,"passed_time":0.1987853318,"remaining_time":0.6192613012},
{"learn":[4.630491517],"iteration":243,"passed_time":0.1992514704,"remaining_time":0.6173529164},
{"learn":[4.627813333],"iteration":244,"passed_time":0.1997112018,"remaining_time":0.6154365606},
{"learn":[4.622496304],"iteration":245,"passed_time":0.2002644871,"remaining_time":0.6138187937},
{"learn":[4.618979301],"iteration":246,"passed_time":0.2008106673,"remaining_time":0.6121879856},
{"learn":[4.616563458],"iteration":247,"passed_time":0.2012776573,"remaining_time":0.6103257994},
{"learn":[4.614759385],"iteration":248,"passed_time":0.201733391,"remaining_time":0.6084408699},
{"learn":[4.61251363],"iteration":249,"passed_time":0.2021858806,"remaining_time":0.6065576418},
{"learn":[4.608796693],"iteration":250,"passed_time":0.2026712385,"remaining_time":0.6047838949},
{"learn":[4.60847774],"iteration":251,"passed_time":0.2031058087,"remaining_time":0.6028696226},
{"learn":[4.605195659],"iteration":252,"passed_time":0.2035587623,"remaining_time":0.601021326},
{"learn":[4.60103766],"iteration":253,"passed_time":0.2040197912,"remaining_time":0.5992077332},
{"learn":[4.599325598],"iteration":254,"passed_time":0.2044933334,"remaining_time":0.5974413074},
{"learn":[4.597012808],"iteration":255,"passed_time":0.2049346256,"remaining_time":0.5955912557},
{"learn":[4.594161533],"iteration":256,"passed_time":0.2054126051,"remaining_time":0.5938582319},
{"learn":[4.592197259],"iteration":257,"passed_time":0.2058601955,"remaining_time":0.5920475389},
{"learn":[4.58952828],"iteration":258,"passed_time":0.2063167943,"remaining_time":0.590273145},
{"learn":[4.585816572],"iteration":259,"passed_time":0.2067797465,"remaining_time":0.5885269707},
{"learn":[4.582934052],"iteration":260,"passed_time":0.2073963993,"remaining_time":0.5872258202},
{"learn":[4.582234842],"iteration":261,"passed_time":0.2078769644,"remaining_time":0.585546564},
{"learn":[4.57571562],"iteration":262,"passed_time":0.2083501119,"remaining_time":0.5838556369},
{"learn":[4.571197349],"iteration":263,"passed_time":0.2088248285,"remaining_time":0.5821783099},
{"learn":[4.56723703],"iteration":264,"passed_time":0.2092689597,"remaining_time":0.5804252279},
{"learn":[4.560335567],"iteration":265,"passed_time":0.20973797,"remaining_time":0.5787506391},
{"learn":[4.554709345],"iteration":266,"passed_time":0.2101881853,"remaining_time":0.5770334826},
{"learn":[4.552806306],"iteration":267,"passed_time":0.2106507821,"remaining_time":0.575359599},
{"learn":[4.550766241],"iteration":268,"passed_time":0.2111958167,"remaining_time":0.5739187436},
{"learn":[4.549216045],"iteration":269,"passed_time":0.211770407,"remaining_time":0.5725644337},
{"learn":[4.547687452],"iteration":270,"passed_time":0.212234655,"remaining_time":0.5709190536},
{"learn":[4.545642435],"iteration":271,"passed_time":0.2126835272,"remaining_time":0.5692412052},
{"learn":[4.543930359],"iteration":272,"passed_time":0.213139291,"remaining_time":0.5675907126},
{"learn":[4.541029943],"iteration":273,"passed_time":0.2136354824,"remaining_time":0.5660560593},
{"learn":[4.537781449],"iteration":274,"passed_time":0.214221817,"remaining_time":0.5647666086},
{"learn":[4.53066128],"iteration":275,"passed_time":0.2147445706,"remaining_time":0.5633154678},
{"learn":[4.526763956],"iteration":276,"passed_time":0.2152168967,"remaining_time":0.561739409},
{"learn":[4.522036004],"iteration":277,"passed_time":0.2156898678,"remaining_time":0.5601729661},
{"learn":[4.515307629],"iteration":278,"passed_time":0.2161708766,"remaining_time":0.5586351327},
{"learn":[4.51109143],"iteration":279,"passed_time":0.2166774625,"remaining_time":0.5571706178},
{"learn":[4.508233494],"iteration":280,"passed_time":0.2171323299,"remaining_time":0.5555805878},
{"learn":[4.502555629],"iteration":281,"passed_time":0.2175849381,"remaining_time":0.5539928566},
{"learn":[4.500081355],"iteration":282,"passed_time":0.2180454765,"remaining_time":0.5524332392},
{"learn":[4.495281743],"iteration":283,"passed_time":0.2185239665,"remaining_time":0.5509266198},
{"learn":[4.492138869],"iteration":284,"passed_time":0.2190001805,"remaining_time":0.5494215055},
{"learn":[4.491708261],"iteration":285,"passed_time":0.2194466794,"remaining_time":0.5478494024},
{"learn":[4.489398865],"iteration":286,"passed_time":0.2198955508,"remaining_time":0.5462910373},
{"learn":[4.485796373],"iteration":287,"passed_time":0.2203573486,"remaining_time":0.544772334},
{"learn":[4.479542205],"iteration":288,"passed_time":0.2208445244,"remaining_time":0.5433233801},
{"learn":[4.475986993],"iteration":289,"passed_time":0.2214621677,"remaining_time":0.5422004796},
{"learn":[4.468661855],"iteration":290,"passed_time":0.2219616289,"remaining_time":0.5407931095},
{"learn":[4.463785664],"iteration":291,"passed_time":0.2224257499,"remaining_time":0.5393062703},
{"learn":[4.460445831],"iteration":292,"passed_time":0.2228913555,"remaining_time":0.5378299944},
{"learn":[4.45692492],"iteration":293,"passed_time":0.2233552534,"remaining_time":0.5363564928},
{"learn":[4.454031688],"iteration":294,"passed_time":0.2238255078,"remaining_time":0.5349050272},
{"learn":[4.451672391],"iteration":295,"passed_time":0.2242967292,"remaining_time":0.5334624911},
{"learn":[4.45031553],"iteration":296,"passed_time":0.224754946,"remaining_time":0.5319957139},
{"learn":[4.446782666],"iteration":297,"passed_time":0.2252156046,"remaining_time":0.5305414579},
{"learn":[4.444369689],"iteration":298,"passed_time":0.225804349,"remaining_time":0.5293941427},
{"learn":[4.44411683],"iteration":299,"passed_time":0.2263133631,"remaining_time":0.528064514},
{"learn":[4.440876943],"iteration":300,"passed_time":0.2268005778,"remaining_time":0.526689714},
{"learn":[4.439336453],"iteration":301,"passed_time":0.2272561697,"remaining_time":0.5252477034},
{"learn":[4.436666901],"iteration":302,"passed_time":0.2277272776,"remaining_time":0.5238478961},
{"learn":[4.433043336],"iteration":303,"passed_time":0.2281886611,"remaining_time":0.5224319347},
{"learn":[4.431419305],"iteration":304,"passed_time":0.2286482635,"remaining_time":0.5210181742},
{"learn":[4.428859646],"iteration":305,"passed_time":0.2291020286,"remaining_time":0.5195974113},
{"learn":[4.424552441],"iteration":306,"passed_time":0.2295611325,"remaining_time":0.5181949995},
{"learn":[4.422706391],"iteration":307,"passed_time":0.2300170914,"remaining_time":0.5167916469},
{"learn":[4.421427994],"iteration":308,"passed_time":0.230469759,"remaining_time":0.5153870662},
{"learn":[4.418733158],"iteration":309,"passed_time":0.2309291129,"remaining_time":0.5140035095},
{"learn":[4.415656941],"iteration":310,"passed_time":0.2313907072,"remaining_time":0.5126308594},
{"learn":[4.410747417],"iteration":311,"passed_time":0.2318723979,"remaining_time":0.5113083646},
{"learn":[4.408126521],"iteration":312,"passed_time":0.2323264026,"remaining_time":0.5099304747},
{"learn":[4.407843853],"iteration":313,"passed_time":0.2327729888,"remaining_time":0.5085422622},
{"learn":[4.405219398],"iteration":314,"passed_time":0.2332338722,"remaining_time":0.507191119},
{"learn":[4.402708465],"iteration":315,"passed_time":0.2336988155,"remaining_time":0.5058543981},
{"learn":[4.40104971],"iteration":316,"passed_time":0.2341582917,"remaining_time":0.5045113982},
{"learn":[4.400830038],"iteration":317,"passed_time":0.2346074961,"remaining_time":0.5031519255},
{"learn":[4.39784288],"iteration":318,"passed_time":0.2351011964,"remaining_time":0.5018931497},
{"learn":[4.393741845],"iteration":319,"passed_time":0.2355534513,"remaining_time":0.5005510839},
{"learn":[4.393425936],"iteration":320,"passed_time":0.2359991511,"remaining_time":0.4992006966},
{"learn":[4.390505974],"iteration":321,"passed_time":0.2364684127,"remaining_time":0.4979055398},
{"learn":[4.390305136],"iteration":322,"passed_time":0.2369090506,"remaining_time":0.4965555023},
{"learn":[4.38568203],"iteration":323,"passed_time":0.2373851797,"remaining_time":0.4952851279},
{"learn":[4.383057135],"iteration":324,"passed_time":0.2378334564,"remaining_time":0.4939617941},
{"learn":[4.380662684],"iteration":325,"passed_time":0.2382928184,"remaining_time":0.4926667472},
{"learn":[4.37805727],"iteration":326,"passed_time":0.2387533164,"remaining_time":0.4913791496},
{"learn":[4.373708319],"iteration":327,"passed_time":0.239219299,"remaining_time":0.4901078321},
{"learn":[4.36887921],"iteration":328,"passed_time":0.2396799276,"remaining_time":0.4888304906},
{"learn":[4.367895929],"iteration":329,"passed_time":0.2401573144,"remaining_time":0.4875921233},
{"learn":[4.362140573],"iteration":330,"passed_time":0.2406744494,"remaining_time":0.4864386909},
{"learn":[4.361931924],"iteration":331,"passed_time":0.2411337645,"remaining_time":0.4851727552},
{"learn":[4.359656377],"iteration":332,"passed_time":0.2415950767,"remaining_time":0.4839156642},
{"learn":[4.354281355],"iteration":333,"passed_time":0.2420549676,"remaining_time":0.4826605043},
{"learn":[4.348589447],"iteration":334,"passed_time":0.2425186206,"remaining_time":0.4814175604},
{"learn":[4.346355698],"iteration":335,"passed_time":0.2429916916,"remaining_time":0.4801978667},
{"learn":[4.343894047],"iteration":336,"passed_time":0.2434657787,"remaining_time":0.4789846032},
{"learn":[4.341561356],"iteration":337,"passed_time":0.2439243113,"remaining_time":0.4777452487},
{"learn":[4.338869061],"iteration":338,"passed_time":0.2443718335,"remaining_time":0.4764890323},
{"learn":[4.333720063],"iteration":339,"passed_time":0.2448395628,"remaining_time":0.4752767984},
{"learn":[4.330892223],"iteration":340,"passed_time":0.2452955706,"remaining_time":0.4740462786},
{"learn":[4.328311474],"iteration":341,"passed_time":0.2457687473,"remaining_time":0.4728533208},
{"learn":[4.324580133],"iteration":342,"passed_time":0.2462135524,"remaining_time":0.4716102156},
{"learn":[4.323354432],"iteration":343,"passed_time":0.2466715777,"remaining_time":0.4703969621},
{"learn":[4.323159553],"iteration":344,"passed_time":0.2471363479,"remaining_time":0.4692008923},
{"learn":[4.318639682],"iteration":345,"passed_time":0.2476148643,"remaining_time":0.4680350325},
{"learn":[4.312712208],"iteration":346,"passed_time":0.248068556,"remaining_time":0.4668264181},
{"learn":[4.311461062],"iteration":347,"passed_time":0.2485188415,"remaining_time":0.4656157604},
{"learn":[4.311178356],"iteration":348,"passed_time":0.2489757308,"remaining_time":0.4644217786},
{"learn":[4.311102505],"iteration":349,"passed_time":0.2494059394,"remaining_time":0.4631824588},
{"learn":[4.310232308],"iteration":350,"passed_time":0.2498693804,"remaining_time":0.4620091963},
{"learn":[4.305128197],"iteration":351,"passed_time":0.250319611,"remaining_time":0.4608156475},
{"learn":[4.304595496],"iteration":352,"passed_time":0.2507656426,"remaining_time":0.4596186141},
{"learn":[4.3004992],"iteration":353,"passed_time":0.2512289715,"remaining_time":0.4584573887},
{"learn":[4.297581524],"iteration":354,"passed_time":0.2516788783,"remaining_time":0.4572757084},
{"learn":[4.297355825],"iteration":355,"passed_time":0.2521151057,"remaining_time":0.4560733935},
{"learn":[4.295758715],"iteration":356,"passed_time":0.2525875724,"remaining_time":0.4549406417},
{"learn":[4.292500657],"iteration":357,"passed_time":0.2530424334,"remaining_time":0.4537800063},
{"learn":[4.290797586],"iteration":358,"passed_time":0.253558285,"remaining_time":0.4527322024},
{"learn":[4.286410608],"iteration":359,"passed_time":0.2540572348,"remaining_time":0.4516573064},
{"learn":[4.280278245],"iteration":360,"passed_time":0.2545915312,"remaining_time":0.4506481674},
{"learn":[4.279941283],"iteration":361,"passed_time":0.2551153117,"remaining_time":0.4496231184},
{"learn":[4.274426275],"iteration":362,"passed_time":0.2555768134,"remaining_time":0.4484915431},
{"learn":[4.273567658],"iteration":363,"passed_time":0.2560292955,"remaining_time":0.4473478899},
{"learn":[4.269488271],"iteration":364,"passed_time":0.2564818408,"remaining_time":0.446208134},
{"learn":[4.266838205],"iteration":365,"passed_time":0.2569440946,"remaining_time":0.4450889508},
{"learn":[4.263456509],"iteration":366,"passed_time":0.2574227461,"remaining_time":0.4440016301},
{"learn":[4.260360204],"iteration":367,"passed_time":0.2578703388,"remaining_time":0.4428642775},
{"learn":[4.255120549],"iteration":368,"passed_time":0.2583521281,"remaining_time":0.4417891405},
{"learn":[4.252582211],"iteration":369,"passed_time":0.2588019063,"remaining_time":0.4406627053},
{"learn":[4.247857931],"iteration":370,"passed_time":0.2592656887,"remaining_time":0.4395636609},
{"learn":[4.245288911],"iteration":371,"passed_time":0.2597190936,"remaining_time":0.4384505128},
{"learn":[4.24048515],"iteration":372,"passed_time":0.2601749274,"remaining_time":0.4373449852},
{"learn":[4.2378365],"iteration":373,"passed_time":0.2606377442,"remaining_time":0.43625462},
{"learn":[4.236751063],"iteration":374,"passed_time":0.2610973089,"remaining_time":0.4351621816},
{"learn":[4.233240093],"iteration":375,"passed_time":0.2615699379,"remaining_time":0.4340947906},
{"learn":[4.230358421],"iteration":376,"passed_time":0.2620376792,"remaining_time":0.4330224779},
{"learn":[4.225853583],"iteration":377,"passed_time":0.2625177275,"remaining_time":0.4319736151},
{"learn":[4.224702126],"iteration":378,"passed_time":0.2629656012,"remaining_time":0.4308750352},
{"learn":[4.224361982],"iteration":379,"passed_time":0.2634093994,"remaining_time":0.4297732305},
{"learn":[4.223787954],"iteration":380,"passed_time":0.263855909,"remaining_time":0.4286792853},
{"learn":[4.22144054],"iteration":381,"passed_time":0.2643121288,"remaining_time":0.4276044387},
{"learn":[4.217739335],"iteration":382,"passed_time":0.264778527,"remaining_time":0.4265492197},
{"learn":[4.215611665],"iteration":383,"passed_time":0.2652329957,"remaining_time":0.4254779305},
{"learn":[4.210236863],"iteration":384,"passed_time":0.2657063912,"remaining_time":0.4244400794},
{"learn":[4.208454294],"iteration":385,"passed_time":0.2661651561,"remaining_time":0.4233818805},
{"learn":[4.207446501],"iteration":386,"passed_time":0.2666212781,"remaining_time":0.4223225929},
{"learn":[4.204985442],"iteration":387,"passed_time":0.2670712013,"remaining_time":0.4212566371},
{"learn":[4.202796622],"iteration":388,"passed_time":0.2675275416,"remaining_time":0.4202039279},
{"learn":[4.199774004],"iteration":389,"passed_time":0.2679791919,"remaining_time":0.4191469411},
{"learn":[4.199458358],"iteration":390,"passed_time":0.2684779097,"remaining_time":0.4181663606},
{"learn":[4.19751254],"iteration":391,"passed_time":0.2689616111,"remaining_time":0.4171649478},
{"learn":[4.195201346],"iteration":392,"passed_time":0.2694466945,"remaining_time":0.4161683042},
{"learn":[4.190593508],"iteration":393,"passed_time":0.2699738925,"remaining_time":0.4152390327},
{"learn":[4.187212054],"iteration":394,"passed_time":0.270553903,"remaining_time":0.4143926869},
{"learn":[4.184984466],"iteration":395,"passed_time":0.2710911336,"remaining_time":0.4134824362},
{"learn":[4.182832144],"iteration":396,"passed_time":0.2716298545,"remaining_time":0.4125763281},
{"learn":[4.179752812],"iteration":397,"passed_time":0.2720963568,"remaining_time":0.4115628312},
{"learn":[4.17878934],"iteration":398,"passed_time":0.2725550757,"remaining_time":0.4105403521},
{"learn":[4.174548229],"iteration":399,"passed_time":0.2730258747,"remaining_time":0.4095388121},
{"learn":[4.168872556],"iteration":400,"passed_time":0.2735063521,"remaining_time":0.4085543764},
{"learn":[4.163926494],"iteration":401,"passed_time":0.2739721789,"remaining_time":0.4075506542},
{"learn":[4.159485076],"iteration":402,"passed_time":0.2744380634,"remaining_time":0.406549687},
{"learn":[4.155926102],"iteration":403,"passed_time":0.2748994016,"remaining_time":0.4055446618},
{"learn":[4.153540115],"iteration":404,"passed_time":0.2753842426,"remaining_time":0.4045768503},
{"learn":[4.150983044],"iteration":405,"passed_time":0.2758471035,"remaining_time":0.4035792598},
{"learn":[4.146539132],"iteration":406,"passed_time":0.2763261704,"remaining_time":0.4026079093},
{"learn":[4.144869174],"iteration":407,"passed_time":0.2768179583,"remaining_time":0.4016574296},
{"learn":[4.142825962],"iteration":408,"passed_time":0.2773752525,"remaining_time":0.400803849},
{"learn":[4.142467378],"iteration":409,"passed_time":0.2778680004,"remaining_time":0.3998588298},
{"learn":[4.141800768],"iteration":410,"passed_time":0.2783196899,"remaining_time":0.3988571711},
{"learn":[4.140107084],"iteration":411,"passed_time":0.2788034221,"remaining_time":0.3979039131},
{"learn":[4.136243196],"iteration":412,"passed_time":0.2793008541,"remaining_time":0.3969724004},
{"learn":[4.133618439],"iteration":413,"passed_time":0.2797604449,"remaining_time":0.395989422},
{"learn":[4.131053025],"iteration":414,"passed_time":0.2802268619,"remaining_time":0.3950185885},
{"learn":[4.128379975],"iteration":415,"passed_time":0.2806957424,"remaining_time":0.3940536384},
{"learn":[4.127068571],"iteration":416,"passed_time":0.2811586726,"remaining_time":0.3930827485},
{"learn":[4.125969877],"iteration":417,"passed_time":0.2816063804,"remaining_time":0.3920930942},
{"learn":[4.123893633],"iteration":418,"passed_time":0.2820935049,"remaining_time":0.3911606834},
{"learn":[4.119643722],"iteration":419,"passed_time":0.2825621506,"remaining_time":0.3902048746},
{"learn":[4.11465686],"iteration":420,"passed_time":0.283018275,"remaining_time":0.3892341596},
{"learn":[4.111565986],"iteration":421,"passed_time":0.2834767602,"remaining_time":0.3882691171},
{"learn":[4.106322452],"iteration":422,"passed_time":0.2840010276,"remaining_time":0.3873962008},
{"learn":[4.104222175],"iteration":423,"passed_time":0.2845715227,"remaining_time":0.386587729},
{"learn":[4.103008002],"iteration":424,"passed_time":0.2850374377,"remaining_time":0.3856388863},
{"learn":[4.099176337],"iteration":425,"passed_time":0.2855110596,"remaining_time":0.3847026953},
{"learn":[4.096525716],"iteration":426,"passed_time":0.2859846595,"remaining_time":0.3837686414},
{"learn":[4.094967724],"iteration":427,"passed_time":0.286468683,"remaining_time":0.3828506699},
{"learn":[4.094683584],"iteration":428,"passed_time":0.2869239171,"remaining_time":0.3818964024},
{"learn":[4.091096563],"iteration":429,"passed_time":0.2873632379,"remaining_time":0.3809233618},
{"learn":[4.089178677],"iteration":430,"passed_time":0.2878275989,"remaining_time":0.3799858557},
{"learn":[4.085335077],"iteration":431,"passed_time":0.2882814077,"remaining_time":0.3790366657},
{"learn":[4.084852122],"iteration":432,"passed_time":0.2887410177,"remaining_time":0.3780973604},
{"learn":[4.080322952],"iteration":433,"passed_time":0.2892116817,"remaining_time":0.3771746816},
{"learn":[4.077449519],"iteration":434,"passed_time":0.2896810418,"remaining_time":0.3762523876},
{"learn":[4.076568374],"iteration":435,"passed_time":0.2901418207,"remaining_time":0.3753210708},
{"learn":[4.076071793],"iteration":436,"passed_time":0.2905884045,"remaining_time":0.3743736195},
{"learn":[4.075027644],"iteration":437,"passed_time":0.2910546115,"remaining_time":0.373453634},
{"learn":[4.07020837],"iteration":438,"passed_time":0.2915231863,"remaining_time":0.3725387415},
{"learn":[4.06833694],"iteration":439,"passed_time":0.2920057153,"remaining_time":0.3716436376},
{"learn":[4.063936568],"iteration":440,"passed_time":0.2924711842,"remaining_time":0.37072878},
{"learn":[4.061734926],"iteration":441,"passed_time":0.2929212188,"remaining_time":0.3697964708},
{"learn":[4.060815619],"iteration":442,"passed_time":0.2933768207,"remaining_time":0.3688733389},
{"learn":[4.056407489],"iteration":443,"passed_time":0.2938255482,"remaining_time":0.3679437045},
{"learn":[4.05238936],"iteration":444,"passed_time":0.2942946347,"remaining_time":0.367041623},
{"learn":[4.049685254],"iteration":445,"passed_time":0.2947613594,"remaining_time":0.3661385496},
{"learn":[4.045162016],"iteration":446,"passed_time":0.2952222893,"remaining_time":0.3652302595},
{"learn":[4.042955482],"iteration":447,"passed_time":0.2956985326,"remaining_time":0.3643428348},
{"learn":[4.041467663],"iteration":448,"passed_time":0.2961810127,"remaining_time":0.3634648953},
{"learn":[4.038920476],"iteration":449,"passed_time":0.2966327218,"remaining_time":0.3625511044},
{"learn":[4.036694383],"iteration":450,"passed_time":0.2970850752,"remaining_time":0.361640147},
{"learn":[4.034999007],"iteration":451,"passed_time":0.2975377308,"remaining_time":0.3607315851},
{"learn":[4.031928018],"iteration":452,"passed_time":0.2981172696,"remaining_time":0.3599782483},
{"learn":[4.028718143],"iteration":453,"passed_time":0.2986473514,"remaining_time":0.359166198},
{"learn":[4.027401978],"iteration":454,"passed_time":0.299138382,"remaining_time":0.3583086114},
{"learn":[4.025930598],"iteration":455,"passed_time":0.2995966657,"remaining_time":0.3574135661},
{"learn":[4.021074523],"iteration":456,"passed_time":0.3000612603,"remaining_time":0.3565279308},
{"learn":[4.020268486],"iteration":457,"passed_time":0.3005226623,"remaining_time":0.3556403558},
{"learn":[4.017986361],"iteration":458,"passed_time":0.3009749997,"remaining_time":0.3547439538},
{"learn":[4.014814804],"iteration":459,"passed_time":0.3014177035,"remaining_time":0.3538381737},
{"learn":[4.009704796],"iteration":460,"passed_time":0.3019003146,"remaining_time":0.352981062},
{"learn":[4.008440457],"iteration":461,"passed_time":0.3023442102,"remaining_time":0.3520804872},
{"learn":[4.004854849],"iteration":462,"passed_time":0.3028042438,"remaining_time":0.3512006024},
{"learn":[4.000898028],"iteration":463,"passed_time":0.3032622017,"remaining_time":0.3503201295},
{"learn":[3.996617985],"iteration":464,"passed_time":0.3037209694,"remaining_time":0.3494424057},
{"learn":[3.995443319],"iteration":465,"passed_time":0.3041892942,"remaining_time":0.3485774315},
{"learn":[3.990771995],"iteration":466,"passed_time":0.3046501996,"remaining_time":0.3477056882},
{"learn":[3.989249359],"iteration":467,"passed_time":0.3051835928,"remaining_time":0.3469181013},
{"learn":[3.986599538],"iteration":468,"passed_time":0.3057488725,"remaining_time":0.3461677},
{"learn":[3.985628919],"iteration":469,"passed_time":0.3063087348,"remaining_time":0.3454119776},
{"learn":[3.985086112],"iteration":470,"passed_time":0.3067723742,"remaining_time":0.3445490148},
{"learn":[3.98466839],"iteration":471,"passed_time":0.3072275033,"remaining_time":0.343678224},
{"learn":[3.984233894],"iteration":472,"passed_time":0.3076705197,"remaining_time":0.3427956953},
{"learn":[3.981855845],"iteration":473,"passed_time":0.3081419406,"remaining_time":0.3419465417},
{"learn":[3.978684264],"iteration":474,"passed_time":0.3085964133,"remaining_time":0.3410802463},
{"learn":[3.974361269],"iteration":475,"passed_time":0.3090781898,"remaining_time":0.3402457383},
{"learn":[3.972074049],"iteration":476,"passed_time":0.3095540864,"remaining_time":0.3394062625},
{"learn":[3.97191982],"iteration":477,"passed_time":0.3100139894,"remaining_time":0.3385508419},
{"learn":[3.969616848],"iteration":478,"passed_time":0.3104945665,"remaining_time":0.3377195598},
{"learn":[3.968533527],"iteration":479,"passed_time":0.3109521078,"remaining_time":0.3368647834},
{"learn":[3.967568753],"iteration":480,"passed_time":0.3114166812,"remaining_time":0.3360192464},
{"learn":[3.966232553],"iteration":481,"passed_time":0.3118745097,"remaining_time":0.3351680415},
{"learn":[3.961522393],"iteration":482,"passed_time":0.3123325482,"remaining_time":0.3343186903},
{"learn":[3.955829553],"iteration":483,"passed_time":0.312788112,"remaining_time":0.3334683177},
{"learn":[3.954248095],"iteration":484,"passed_time":0.3133073438,"remaining_time":0.3326871795},
{"learn":[3.951922606],"iteration":485,"passed_time":0.3138135106,"remaining_time":0.3318933013},
{"learn":[3.94978202],"iteration":486,"passed_time":0.3142994427,"remaining_time":0.3310792897},
{"learn":[3.949518999],"iteration":487,"passed_time":0.3147619325,"remaining_time":0.3302420275},
{"learn":[3.945431216],"iteration":488,"passed_time":0.3152436023,"remaining_time":0.3294263411},
{"learn":[3.943249086],"iteration":489,"passed_time":0.3157087147,"remaining_time":0.3285947847},
{"learn":[3.941981548],"iteration":490,"passed_time":0.3161886448,"remaining_time":0.3277800818},
{"learn":[3.936600517],"iteration":491,"passed_time":0.3166511826,"remaining_time":0.3269487821},
{"learn":[3.934476885],"iteration":492,"passed_time":0.3171287526,"remaining_time":0.3261344373},
{"learn":[3.93045798],"iteration":493,"passed_time":0.3175927586,"remaining_time":0.3253075625},
{"learn":[3.925977375],"iteration":494,"passed_time":0.3180543801,"remaining_time":0.3244797212},
{"learn":[3.92457993],"iteration":495,"passed_time":0.3185124815,"remaining_time":0.3236497796},
{"learn":[3.919849146],"iteration":496,"passed_time":0.3189655482,"remaining_time":0.3228162389},
{"learn":[3.919681964],"iteration":497,"passed_time":0.3194228698,"remaining_time":0.3219885154},
{"learn":[3.917633027],"iteration":498,"passed_time":0.3198822242,"remaining_time":0.3211643173},
{"learn":[3.916616419],"iteration":499,"passed_time":0.3203465632,"remaining_time":0.3203465632},
{"learn":[3.912896166],"iteration":500,"passed_time":0.320819155,"remaining_time":0.3195384398},
{"learn":[3.912769674],"iteration":501,"passed_time":0.3212611584,"remaining_time":0.3187013086},
{"learn":[3.909373788],"iteration":502,"passed_time":0.3217242449,"remaining_time":0.3178865799},
{"learn":[3.906706036],"iteration":503,"passed_time":0.322193591,"remaining_time":0.317079407},
{"learn":[3.903895664],"iteration":504,"passed_time":0.3226563501,"remaining_time":0.3162671154},
{"learn":[3.902982967],"iteration":505,"passed_time":0.3230991882,"remaining_time":0.3154367568},
{"learn":[3.900905528],"iteration":506,"passed_time":0.3235507546,"remaining_time":0.3146164143},
{"learn":[3.897463465],"iteration":507,"passed_time":0.3240114053,"remaining_time":0.3138063216},
{"learn":[3.895918033],"iteration":508,"passed_time":0.3244670568,"remaining_time":0.3129927797},
{"learn":[3.893921936],"iteration":509,"passed_time":0.3249493117,"remaining_time":0.3122062014},
{"learn":[3.890237934],"iteration":510,"passed_time":0.3254047953,"remaining_time":0.3113951955},
{"learn":[3.887311613],"iteration":511,"passed_time":0.3258919852,"remaining_time":0.3106157984},
{"learn":[3.884869735],"iteration":512,"passed_time":0.3263901417,"remaining_time":0.3098479513},
{"learn":[3.882101231],"iteration":513,"passed_time":0.3268373942,"remaining_time":0.3090330226},
{"learn":[3.88060368],"iteration":514,"passed_time":0.3273218574,"remaining_time":0.3082545647},
{"learn":[3.877726076],"iteration":515,"passed_time":0.3278462001,"remaining_time":0.3075146528},
{"learn":[3.874938145],"iteration":516,"passed_time":0.328325578,"remaining_time":0.306733567},
{"learn":[3.874340833],"iteration":517,"passed_time":0.3287835423,"remaining_time":0.3059337208},
{"learn":[3.873105224],"iteration":518,"passed_time":0.3292345334,"remaining_time":0.3051287294},
{"learn":[3.869800236],"iteration":519,"passed_time":0.3297146249,"remaining_time":0.3043519615},
{"learn":[3.867932518],"iteration":520,"passed_time":0.3301979344,"remaining_time":0.303579291},
{"learn":[3.866666962],"iteration":521,"passed_time":0.3306678551,"remaining_time":0.3027954689},
{"learn":[3.865527652],"iteration":522,"passed_time":0.3311270524,"remaining_time":0.3020030669},
{"learn":[3.861900081],"iteration":523,"passed_time":0.331581992,"remaining_time":0.301208069},
{"learn":[3.858502887],"iteration":524,"passed_time":0.3320460998,"remaining_time":0.3004226617},
{"learn":[3.858335097],"iteration":525,"passed_time":0.3324904369,"remaining_time":0.2996206599},
{"learn":[3.855719306],"iteration":526,"passed_time":0.3329475878,"remaining_time":0.2988315162},
{"learn":[3.855137428],"iteration":527,"passed_time":0.3334100981,"remaining_time":0.298048421},
{"learn":[3.851985706],"iteration":528,"passed_time":0.3338955205,"remaining_time":0.2972869379},
{"learn":[3.851051809],"iteration":529,"passed_time":0.3343408028,"remaining_time":0.2964909006},
{"learn":[3.850679146],"iteration":530,"passed_time":0.334774893,"remaining_time":0.2956862991},
{"learn":[3.848179484],"iteration":531,"passed_time":0.3352276687,"remaining_time":0.2948995281},
{"learn":[3.844551071],"iteration":532,"passed_time":0.3356919997,"remaining_time":0.2941241348},
{"learn":[3.841604794],"iteration":533,"passed_time":0.3361433242,"remaining_time":0.2933385563},
{"learn":[3.83969656],"iteration":534,"passed_time":0.3366072905,"remaining_time":0.2925652151},
{"learn":[3.836811463],"iteration":535,"passed_time":0.3370754217,"remaining_time":0.2917966337},
{"learn":[3.834182551],"iteration":536,"passed_time":0.3375605472,"remaining_time":0.2910438238},
{"learn":[3.828012842],"iteration":537,"passed_time":0.3380111752,"remaining_time":0.2902623847},
{"learn":[3.826636176],"iteration":538,"passed_time":0.3384641966,"remaining_time":0.2894842201},
{"learn":[3.826189798],"iteration":539,"passed_time":0.3389263543,"remaining_time":0.2887150425},
{"learn":[3.824104738],"iteration":540,"passed_time":0.3393836358,"remaining_time":0.2879428629},
{"learn":[3.82300218],"iteration":541,"passed_time":0.3398618108,"remaining_time":0.2871895007},
{"learn":[3.817146402],"iteration":542,"passed_time":0.3403075536,"remaining_time":0.2864098563},
{"learn":[3.814638044],"iteration":543,"passed_time":0.3407564999,"remaining_time":0.2856341249},
{"learn":[3.812979573],"iteration":544,"passed_time":0.3412140468,"remaining_time":0.284866773},
{"learn":[3.811938825],"iteration":545,"passed_time":0.3417373464,"remaining_time":0.2841552295},
{"learn":[3.811479418],"iteration":546,"passed_time":0.3421892759,"remaining_time":0.2833852687},
{"learn":[3.80742981],"iteration":547,"passed_time":0.3426377126,"remaining_time":0.2826135877},
{"learn":[3.805097043],"iteration":548,"passed_time":0.3431052415,"remaining_time":0.2818587685},
{"learn":[3.801577232],"iteration":549,"passed_time":0.3435976344,"remaining_time":0.2811253372},
{"learn":[3.799762083],"iteration":550,"passed_time":0.3440742499,"remaining_time":0.2803799241},
{"learn":[3.796393455],"iteration":551,"passed_time":0.3445318067,"remaining_time":0.2796200171},
{"learn":[3.793486459],"iteration":552,"passed_time":0.3449800655,"remaining_time":0.2788536876},
{"learn":[3.792006091],"iteration":553,"passed_time":0.3454469216,"remaining_time":0.2781034784},
{"learn":[3.78932128],"iteration":554,"passed_time":0.345916745,"remaining_time":0.2773566694},
{"learn":[3.787581812],"iteration":555,"passed_time":0.3464013848,"remaining_time":0.2766226886},
{"learn":[3.785308865],"iteration":556,"passed_time":0.346883818,"remaining_time":0.2758878481},
{"learn":[3.78465475],"iteration":557,"passed_time":0.3473435927,"remaining_time":0.2751359641},
{"learn":[3.780498869],"iteration":558,"passed_time":0.3477892589,"remaining_time":0.274373995},
{"learn":[3.778734909],"iteration":559,"passed_time":0.348269681,"remaining_time":0.2736404637},
{"learn":[3.778652349],"iteration":560,"passed_time":0.3487013434,"remaining_time":0.2728696787},
{"learn":[3.777928006],"iteration":561,"passed_time":0.3491385093,"remaining_time":0.2721043898},
{"learn":[3.776131406],"iteration":562,"passed_time":0.3495793034,"remaining_time":0.2713430828},
{"learn":[3.772925617],"iteration":563,"passed_time":0.3500454544,"remaining_time":0.2706025144},
{"learn":[3.7727745],"iteration":564,"passed_time":0.3504943779,"remaining_time":0.2698496538},
{"learn":[3.771763073],"iteration":565,"passed_time":0.3509517408,"remaining_time":0.2691043383},
{"learn":[3.768738162],"iteration":566,"passed_time":0.3514088589,"remaining_time":0.2683598517},
{"learn":[3.767220794],"iteration":567,"passed_time":0.3518625342,"remaining_time":0.2676137584},
{"learn":[3.766691102],"iteration":568,"passed_time":0.3523084537,"remaining_time":0.2668628182},
{"learn":[3.766259335],"iteration":569,"passed_time":0.3527550243,"remaining_time":0.2661134394},
{"learn":[3.76116362],"iteration":570,"passed_time":0.3532134514,"remaining_time":0.2653740292},
{"learn":[3.758633056],"iteration":571,"passed_time":0.3536701039,"remaining_time":0.2646342735},
{"learn":[3.754603809],"iteration":572,"passed_time":0.3541358546,"remaining_time":0.263902286},
{"learn":[3.754070549],"iteration":573,"passed_time":0.3545902427,"remaining_time":0.2631627934},
{"learn":[3.750534319],"iteration":574,"passed_time":0.3550747551,"remaining_time":0.2624465581},
{"learn":[3.746491516],"iteration":575,"passed_time":0.3555401187,"remaining_time":0.2617170318},
{"learn":[3.744210544],"iteration":576,"passed_time":0.356006248,"remaining_time":0.2609889825},
{"learn":[3.742929991],"iteration":577,"passed_time":0.3564573144,"remaining_time":0.260250842},
{"learn":[3.740402992],"iteration":578,"passed_time":0.3569517781,"remaining_time":0.259545248},
{"learn":[3.739644243],"iteration":579,"passed_time":0.3574102473,"remaining_time":0.258814317},
{"learn":[3.737529404],"iteration":580,"passed_time":0.3578785925,"remaining_time":0.2580914462},
{"learn":[3.737196923],"iteration":581,"passed_time":0.3583336698,"remaining_time":0.257359921},
{"learn":[3.733954464],"iteration":582,"passed_time":0.3587853593,"remaining_time":0.2566269208},
{"learn":[3.731608623],"iteration":583,"passed_time":0.359239457,"remaining_time":0.2558965995},
{"learn":[3.729843952],"iteration":584,"passed_time":0.3597083142,"remaining_time":0.255177693},
{"learn":[3.727223798],"iteration":585,"passed_time":0.3601833133,"remaining_time":0.254463979},
{"learn":[3.725351667],"iteration":586,"passed_time":0.3606466522,"remaining_time":0.2537428746},
{"learn":[3.725026912],"iteration":587,"passed_time":0.3610966852,"remaining_time":0.2530133237},
{"learn":[3.721974565],"iteration":588,"passed_time":0.3615611597,"remaining_time":0.252294799},
{"learn":[3.720269493],"iteration":589,"passed_time":0.3620285688,"remaining_time":0.2515791749},
{"learn":[3.718907466],"iteration":590,"passed_time":0.3624865985,"remaining_time":0.2508578998},
{"learn":[3.715602912],"iteration":591,"passed_time":0.3629518799,"remaining_time":0.2501425118},
{"learn":[3.714463059],"iteration":592,"passed_time":0.3633930836,"remaining_time":0.2494114419},
{"learn":[3.710802077],"iteration":593,"passed_time":0.3638499501,"remaining_time":0.2486920534},
{"learn":[3.708032435],"iteration":594,"passed_time":0.3643083099,"remaining_time":0.2479745639},
{"learn":[3.703788939],"iteration":595,"passed_time":0.3647573191,"remaining_time":0.2472516056},
{"learn":[3.702500944],"iteration":596,"passed_time":0.3652123644,"remaining_time":0.2465336396},
{"learn":[3.698196925],"iteration":597,"passed_time":0.3656970351,"remaining_time":0.2458364684},
{"learn":[3.69658891],"iteration":598,"passed_time":0.3661575611,"remaining_time":0.2451238431},
{"learn":[3.696124066],"iteration":599,"passed_time":0.36661237,"remaining_time":0.2444082467},
{"learn":[3.693537052],"iteration":600,"passed_time":0.367069103,"remaining_time":0.2436947955},
{"learn":[3.691343275],"iteration":601,"passed_time":0.3675198569,"remaining_time":0.2429782442},
{"learn":[3.690973831],"iteration":602,"passed_time":0.3679771713,"remaining_time":0.2422668939},
{"learn":[3.686151073],"iteration":603,"passed_time":0.3684325167,"remaining_time":0.2415550937},
{"learn":[3.683921982],"iteration":604,"passed_time":0.3689310102,"remaining_time":0.2408723124},
{"learn":[3.679975271],"iteration":605,"passed_time":0.3694022159,"remaining_time":0.2401723978},
{"learn":[3.674047638],"iteration":606,"passed_time":0.3698471929,"remaining_time":0.2394562551},
{"learn":[3.673151794],"iteration":607,"passed_time":0.3703397136,"remaining_time":0.2387716575},
{"learn":[3.670953108],"iteration":608,"passed_time":0.3708373408,"remaining_time":0.2380909692},
{"learn":[3.6703947],"iteration":609,"passed_time":0.3712946208,"remaining_time":0.2373850854},
{"learn":[3.668433805],"iteration":610,"passed_time":0.371788963,"remaining_time":0.2367036115},
{"learn":[3.668304956],"iteration":611,"passed_time":0.3722374834,"remaining_time":0.2359936986},
{"learn":[3.667880012],"iteration":612,"passed_time":0.3726823302,"remaining_time":0.2352823194},
{"learn":[3.667282264],"iteration":613,"passed_time":0.3731317473,"remaining_time":0.2345746815},
{"learn":[3.664611483],"iteration":614,"passed_time":0.3736134505,"remaining_time":0.233888095},
{"learn":[3.662543394],"iteration":615,"passed_time":0.3740799725,"remaining_time":0.2331927101},
{"learn":[3.659041959],"iteration":616,"passed_time":0.3745438799,"remaining_time":0.2324964441},
{"learn":[3.656868545],"iteration":617,"passed_time":0.3751497252,"remaining_time":0.2318886651},
{"learn":[3.654785614],"iteration":618,"passed_time":0.3756213625,"remaining_time":0.2311982861},
{"learn":[3.654566096],"iteration":619,"passed_time":0.376075479,"remaining_time":0.2304978742},
{"learn":[3.651007045],"iteration":620,"passed_time":0.3765599144,"remaining_time":0.2298167594},
{"learn":[3.648921786],"iteration":621,"passed_time":0.3770536468,"remaining_time":0.2291419269},
{"learn":[3.647655706],"iteration":622,"passed_time":0.3775248397,"remaining_time":0.2284540362},
{"learn":[3.647241144],"iteration":623,"passed_time":0.3779918919,"remaining_time":0.2277643451},
{"learn":[3.644195689],"iteration":624,"passed_time":0.3784739981,"remaining_time":0.2270843989},
{"learn":[3.642632246],"iteration":625,"passed_time":0.3789498767,"remaining_time":0.226401364},
{"learn":[3.642523322],"iteration":626,"passed_time":0.3793060084,"remaining_time":0.225647753},
{"learn":[3.641494659],"iteration":627,"passed_time":0.3797557149,"remaining_time":0.2249508375},
{"learn":[3.63976496],"iteration":628,"passed_time":0.3802059458,"remaining_time":0.2242550173},
{"learn":[3.637945652],"iteration":629,"passed_time":0.3806844169,"remaining_time":0.2235765623},
{"learn":[3.636233667],"iteration":630,"passed_time":0.3811701066,"remaining_time":0.2229029625},
{"learn":[3.635304404],"iteration":631,"passed_time":0.381617041,"remaining_time":0.222207391},
{"learn":[3.632234951],"iteration":632,"passed_time":0.3821169025,"remaining_time":0.221543291},
{"learn":[3.631630987],"iteration":633,"passed_time":0.3827532442,"remaining_time":0.2209584974},
{"learn":[3.630301009],"iteration":634,"passed_time":0.3833852937,"remaining_time":0.2203710744},
{"learn":[3.629077964],"iteration":635,"passed_time":0.3839736338,"remaining_time":0.2197584948},
{"learn":[3.628004522],"iteration":636,"passed_time":0.3844835936,"remaining_time":0.2191013257},
{"learn":[3.625062876],"iteration":637,"passed_time":0.384981155,"remaining_time":0.2184375833},
{"learn":[3.624917986],"iteration":638,"passed_time":0.3854953169,"remaining_time":0.2177837393},
{"learn":[3.622887087],"iteration":639,"passed_time":0.3859815827,"remaining_time":0.2171146403},
{"learn":[3.621220865],"iteration":640,"passed_time":0.3865968371,"remaining_time":0.2165183534},
{"learn":[3.621143844],"iteration":641,"passed_time":0.3870614971,"remaining_time":0.2158380311},
{"learn":[3.620822821],"iteration":642,"passed_time":0.3875133107,"remaining_time":0.2151512472},
{"learn":[3.619202826],"iteration":643,"passed_time":0.3879969877,"remaining_time":0.2144828069},
{"learn":[3.618204882],"iteration":644,"passed_time":0.3884599467,"remaining_time":0.2138035366},
{"learn":[3.614259666],"iteration":645,"passed_time":0.388919725,"remaining_time":0.213123193},
{"learn":[3.613415661],"iteration":646,"passed_time":0.3894635215,"remaining_time":0.2124893711},
{"learn":[3.611096773],"iteration":647,"passed_time":0.3899157603,"remaining_time":0.211806092},
{"learn":[3.610820695],"iteration":648,"passed_time":0.3903541307,"remaining_time":0.2111160244},
{"learn":[3.609290065],"iteration":649,"passed_time":0.3908058069,"remaining_time":0.210433896},
{"learn":[3.60897947],"iteration":650,"passed_time":0.3912456687,"remaining_time":0.2097461419},
{"learn":[3.606570702],"iteration":651,"passed_time":0.3917113693,"remaining_time":0.2090729394},
{"learn":[3.606292637],"iteration":652,"passed_time":0.3921563924,"remaining_time":0.2083893846},
{"learn":[3.602753838],"iteration":653,"passed_time":0.3926146116,"remaining_time":0.2077135407},
{"learn":[3.599755869],"iteration":654,"passed_time":0.3930769014,"remaining_time":0.2070405053},
{"learn":[3.599509575],"iteration":655,"passed_time":0.3935473967,"remaining_time":0.2063724154},
{"learn":[3.595337722],"iteration":656,"passed_time":0.3940237514,"remaining_time":0.2057079859},
{"learn":[3.595168561],"iteration":657,"passed_time":0.3944646301,"remaining_time":0.2050256892},
{"learn":[3.59290559],"iteration":658,"passed_time":0.3949428384,"remaining_time":0.2043634414},
{"learn":[3.592015928],"iteration":659,"passed_time":0.3954024271,"remaining_time":0.2036921594},
{"learn":[3.590680403],"iteration":660,"passed_time":0.3958775777,"remaining_time":0.203029499},
{"learn":[3.590361532],"iteration":661,"passed_time":0.39632258,"remaining_time":0.2023520121},
{"learn":[3.589069739],"iteration":662,"passed_time":0.3967736215,"remaining_time":0.2016782963},
{"learn":[3.585010186],"iteration":663,"passed_time":0.3972162878,"remaining_time":0.2010010131},
{"learn":[3.582997552],"iteration":664,"passed_time":0.397679254,"remaining_time":0.2003346618},
{"learn":[3.582119256],"iteration":665,"passed_time":0.39813172,"remaining_time":0.1996636554},
{"learn":[3.579019356],"iteration":666,"passed_time":0.3985931893,"remaining_time":0.1989977991},
{"learn":[3.57719559],"iteration":667,"passed_time":0.3990640007,"remaining_time":0.198337198},
{"learn":[3.574050046],"iteration":668,"passed_time":0.3995378358,"remaining_time":0.1976786602},
{"learn":[3.572204518],"iteration":669,"passed_time":0.4000309263,"remaining_time":0.1970301577},
{"learn":[3.569508025],"iteration":670,"passed_time":0.400927612,"remaining_time":0.1965800065},
{"learn":[3.566268704],"iteration":671,"passed_time":0.4015052259,"remaining_time":0.1959727888},
{"learn":[3.562564052],"iteration":672,"passed_time":0.4021547838,"remaining_time":0.1954006156},
{"learn":[3.561173586],"iteration":673,"passed_time":0.4026550042,"remaining_time":0.1947559813},
{"learn":[3.559551904],"iteration":674,"passed_time":0.4032674986,"remaining_time":0.1941658327},
{"learn":[3.558593054],"iteration":675,"passed_time":0.403866807,"remaining_time":0.193569298},
{"learn":[3.555647008],"iteration":676,"passed_time":0.4044167304,"remaining_time":0.1929491934},
{"learn":[3.553100059],"iteration":677,"passed_time":0.4048805598,"remaining_time":0.1922884074},
{"learn":[3.55085578],"iteration":678,"passed_time":0.4053659797,"remaining_time":0.1916384087},
{"learn":[3.550737965],"iteration":679,"passed_time":0.4058131738,"remaining_time":0.1909709053},
{"learn":[3.549408772],"iteration":680,"passed_time":0.4062957292,"remaining_time":0.1903206133},
{"learn":[3.547390589],"iteration":681,"passed_time":0.4067629961,"remaining_time":0.1896636844},
{"learn":[3.54723575],"iteration":682,"passed_time":0.4072210927,"remaining_time":0.1890030547},
{"learn":[3.543988891],"iteration":683,"passed_time":0.4076919595,"remaining_time":0.1883489169},
{"learn":[3.543868508],"iteration":684,"passed_time":0.4081354884,"remaining_time":0.1876827428},
{"learn":[3.542752124],"iteration":685,"passed_time":0.4086148895,"remaining_time":0.1870336375},
{"learn":[3.541334315],"iteration":686,"passed_time":0.4090712271,"remaining_time":0.1863745183},
{"learn":[3.540208266],"iteration":687,"passed_time":0.4095271202,"remaining_time":0.1857157871},
{"learn":[3.537730983],"iteration":688,"passed_time":0.4100309742,"remaining_time":0.1850792931},
{"learn":[3.53419867],"iteration":689,"passed_time":0.4105776159,"remaining_time":0.1844624072},
{"learn":[3.532628335],"iteration":690,"passed_time":0.4111047599,"remaining_time":0.1838370055},
{"learn":[3.532204987],"iteration":691,"passed_time":0.4116291102,"remaining_time":0.1832106444},
{"learn":[3.530618147],"iteration":692,"passed_time":0.4121138598,"remaining_time":0.1825670346},
{"learn":[3.528909306],"iteration":693,"passed_time":0.4126005777,"remaining_time":0.1819247504},
{"learn":[3.526700678],"iteration":694,"passed_time":0.4130665952,"remaining_time":0.1812738295},
{"learn":[3.526439574],"iteration":695,"passed_time":0.4135077688,"remaining_time":0.1806125887},
{"learn":[3.525784216],"iteration":696,"passed_time":0.4139824822,"remaining_time":0.1799665597},
{"learn":[3.524112693],"iteration":697,"passed_time":0.4144782986,"remaining_time":0.1793301521},
{"learn":[3.522813541],"iteration":698,"passed_time":0.4150023212,"remaining_time":0.1787062928},
{"learn":[3.519148203],"iteration":699,"passed_time":0.4155698279,"remaining_time":0.1781013548},
{"learn":[3.517236747],"iteration":700,"passed_time":0.4161127256,"remaining_time":0.177486027},
{"learn":[3.515603888],"iteration":701,"passed_time":0.4166015078,"remaining_time":0.1768479335},
{"learn":[3.51263524],"iteration":702,"passed_time":0.4171092401,"remaining_time":0.1762182707},
{"learn":[3.51123442],"iteration":703,"passed_time":0.4177311156,"remaining_time":0.1756369463},
{"learn":[3.50828027],"iteration":704,"passed_time":0.4182201446,"remaining_time":0.1749999187},
{"learn":[3.508265537],"iteration":705,"passed_time":0.4185183539,"remaining_time":0.1742838471},
{"learn":[3.506774876],"iteration":706,"passed_time":0.4189971259,"remaining_time":0.1736437877},
{"learn":[3.50552068],"iteration":707,"passed_time":0.4194646889,"remaining_time":0.172999561},
{"learn":[3.501973993],"iteration":708,"passed_time":0.4199502231,"remaining_time":0.1723632086},
{"learn":[3.498880354],"iteration":709,"passed_time":0.4204141887,"remaining_time":0.1717184714},
{"learn":[3.497370959],"iteration":710,"passed_time":0.4208860972,"remaining_time":0.1710774713},
{"learn":[3.496050455],"iteration":711,"passed_time":0.4213421807,"remaining_time":0.170430545},
{"learn":[3.495630067],"iteration":712,"passed_time":0.4217980615,"remaining_time":0.1697840724},
{"learn":[3.49550669],"iteration":713,"passed_time":0.4222523495,"remaining_time":0.1691374957},
{"learn":[3.493652375],"iteration":714,"passed_time":0.4227450072,"remaining_time":0.1685067511},
{"learn":[3.491915684],"iteration":715,"passed_time":0.4232045896,"remaining_time":0.167863273},
{"learn":[3.490303956],"iteration":716,"passed_time":0.4236633132,"remaining_time":0.1672199688},
{"learn":[3.488363853],"iteration":717,"passed_time":0.4241308939,"remaining_time":0.1665806575},
{"learn":[3.485483936],"iteration":718,"passed_time":0.4245870451,"remaining_time":0.165937357},
{"learn":[3.483763466],"iteration":719,"passed_time":0.4250483312,"remaining_time":0.1652965732},
{"learn":[3.481642352],"iteration":720,"passed_time":0.4255289184,"remaining_time":0.1646637562},
{"learn":[3.479826119],"iteration":721,"passed_time":0.4260019958,"remaining_time":0.1640284693},
{"learn":[3.478588728],"iteration":722,"passed_time":0.4264725848,"remaining_time":0.1633926777},
{"learn":[3.475390887],"iteration":723,"passed_time":0.4269469993,"remaining_time":0.1627588008},
{"learn":[3.472636852],"iteration":724,"passed_time":0.4274251399,"remaining_time":0.1621267772},
{"learn":[3.47061883],"iteration":725,"passed_time":0.4278814141,"remaining_time":0.1614869249},
{"learn":[3.46953149],"iteration":726,"passed_time":0.4283488192,"remaining_time":0.1608517574},
{"learn":[3.467217162],"iteration":727,"passed_time":0.4288206196,"remaining_time":0.160218693},
{"learn":[3.465686216],"iteration":728,"passed_time":0.4292850019,"remaining_time":0.1595833135},
{"learn":[3.462631216],"iteration":729,"passed_time":0.4297529415,"remaining_time":0.1589497181},
{"learn":[3.461451053],"iteration":730,"passed_time":0.4304298833,"remaining_time":0.1583934865},
{"learn":[3.458950469],"iteration":731,"passed_time":0.4310305588,"remaining_time":0.1578090024},
{"learn":[3.458072145],"iteration":732,"passed_time":0.431551696,"remaining_time":0.1571955018},
{"learn":[3.454364268],"iteration":733,"passed_time":0.4320365157,"remaining_time":0.1565690915},
{"learn":[3.453243406],"iteration":734,"passed_time":0.4325704126,"remaining_time":0.155960761},
{"learn":[3.453017963],"iteration":735,"passed_time":0.4330843692,"remaining_time":0.1553454803},
{"learn":[3.45201581],"iteration":736,"passed_time":0.4335660519,"remaining_time":0.1547189575},
{"learn":[3.449510107],"iteration":737,"passed_time":0.4340489383,"remaining_time":0.1540932545},
{"learn":[3.447189189],"iteration":738,"passed_time":0.434535665,"remaining_time":0.1534692944},
{"learn":[3.446423605],"iteration":739,"passed_time":0.4350193411,"remaining_time":0.1528446334},
{"learn":[3.445531987],"iteration":740,"passed_time":0.4354972196,"remaining_time":0.1522183264},
{"learn":[3.445328199],"iteration":741,"passed_time":0.4360139006,"remaining_time":0.1516059115},
{"learn":[3.443327544],"iteration":742,"passed_time":0.4365601028,"remaining_time":0.1510039656},
{"learn":[3.441475798],"iteration":743,"passed_time":0.4370818306,"remaining_time":0.1503937482},
{"learn":[3.439046501],"iteration":744,"passed_time":0.4375665117,"remaining_time":0.1497710879},
{"learn":[3.435899469],"iteration":745,"passed_time":0.4382643401,"remaining_time":0.1492213705},
{"learn":[3.433988352],"iteration":746,"passed_time":0.4389203067,"remaining_time":0.1486570784},
{"learn":[3.433413263],"iteration":747,"passed_time":0.4394868771,"remaining_time":0.1480624238},
{"learn":[3.429944699],"iteration":748,"passed_time":0.4400637509,"remaining_time":0.147471297},
{"learn":[3.429291634],"iteration":749,"passed_time":0.4405461107,"remaining_time":0.1468487036},
{"learn":[3.429175603],"iteration":750,"passed_time":0.4410986023,"remaining_time":0.1462497363},
{"learn":[3.428780323],"iteration":751,"passed_time":0.4416059094,"remaining_time":0.1456359914},
{"learn":[3.423893341],"iteration":752,"passed_time":0.4421802316,"remaining_time":0.1450445116},
{"learn":[3.421024316],"iteration":753,"passed_time":0.4427672606,"remaining_time":0.144457223},
{"learn":[3.420969872],"iteration":754,"passed_time":0.4433126687,"remaining_time":0.1438564289},
{"learn":[3.419544785],"iteration":755,"passed_time":0.4437965335,"remaining_time":0.1432359182},
{"learn":[3.417057977],"iteration":756,"passed_time":0.4443858798,"remaining_time":0.1426496285},
{"learn":[3.415160245],"iteration":757,"passed_time":0.4449219156,"remaining_time":0.1420463108},
{"learn":[3.412854597],"iteration":758,"passed_time":0.4454905014,"remaining_time":0.1414535057},
{"learn":[3.410926347],"iteration":759,"passed_time":0.4459828454,"remaining_time":0.140836688},
{"learn":[3.408963843],"iteration":760,"passed_time":0.4464645962,"remaining_time":0.1402168706},
{"learn":[3.407629634],"iteration":761,"passed_time":0.4469529236,"remaining_time":0.1395994696},
{"learn":[3.404384724],"iteration":762,"passed_time":0.4474174922,"remaining_time":0.1389750271},
{"learn":[3.403041656],"iteration":763,"passed_time":0.4478788866,"remaining_time":0.1383500225},
{"learn":[3.401101731],"iteration":764,"passed_time":0.4483418664,"remaining_time":0.1377259328},
{"learn":[3.400890668],"iteration":765,"passed_time":0.4487980974,"remaining_time":0.1371002021},
{"learn":[3.399289941],"iteration":766,"passed_time":0.4492642896,"remaining_time":0.1364779393},
{"learn":[3.399202366],"iteration":767,"passed_time":0.4497054664,"remaining_time":0.1358485263},
{"learn":[3.397447845],"iteration":768,"passed_time":0.4501614518,"remaining_time":0.1352240512},
{"learn":[3.394655341],"iteration":769,"passed_time":0.4506182457,"remaining_time":0.1346002552},
{"learn":[3.393228229],"iteration":770,"passed_time":0.4510701832,"remaining_time":0.13397545},
{"learn":[3.389691197],"iteration":771,"passed_time":0.4515247845,"remaining_time":0.1333518794},
{"learn":[3.389626772],"iteration":772,"passed_time":0.4520117259,"remaining_time":0.1327382429},
{"learn":[3.388480222],"iteration":773,"passed_time":0.4525595902,"remaining_time":0.1321427227},
{"learn":[3.388215066],"iteration":774,"passed_time":0.4530930632,"remaining_time":0.1315431474},
{"learn":[3.386324358],"iteration":775,"passed_time":0.4535649609,"remaining_time":0.1309259681},
{"learn":[3.383913061],"iteration":776,"passed_time":0.4540347742,"remaining_time":0.1303085645},
{"learn":[3.382839768],"iteration":777,"passed_time":0.4545073755,"remaining_time":0.129692336},
{"learn":[3.381961844],"iteration":778,"passed_time":0.4549810552,"remaining_time":0.129076782},
{"learn":[3.381521703],"iteration":779,"passed_time":0.4554460822,"remaining_time":0.1284591514},
{"learn":[3.380918963],"iteration":780,"passed_time":0.4558929016,"remaining_time":0.127836806},
{"learn":[3.377139006],"iteration":781,"passed_time":0.4563684124,"remaining_time":0.1272229078},
{"learn":[3.376004372],"iteration":782,"passed_time":0.4568524708,"remaining_time":0.126611732},
{"learn":[3.373826468],"iteration":783,"passed_time":0.4573147607,"remaining_time":0.125994883},
{"learn":[3.373546786],"iteration":784,"passed_time":0.4578117335,"remaining_time":0.125387927},
{"learn":[3.372109181],"iteration":785,"passed_time":0.4582911835,"remaining_time":0.12477648},
{"learn":[3.370764924],"iteration":786,"passed_time":0.4587564738,"remaining_time":0.1241615361},
{"learn":[3.367833107],"iteration":787,"passed_time":0.459349482,"remaining_time":0.1235813327},
{"learn":[3.36450404],"iteration":788,"passed_time":0.4599131128,"remaining_time":0.1229932406},
{"learn":[3.361794558],"iteration":789,"passed_time":0.4603924026,"remaining_time":0.1223827906},
{"learn":[3.356880529],"iteration":790,"passed_time":0.4608710592,"remaining_time":0.1217725049},
{"learn":[3.353843509],"iteration":791,"passed_time":0.4613648569,"remaining_time":0.1211665281},
{"learn":[3.353640253],"iteration":792,"passed_time":0.4618329549,"remaining_time":0.1205541257},
{"learn":[3.353055088],"iteration":793,"passed_time":0.4622866294,"remaining_time":0.1199383447},
{"learn":[3.351415617],"iteration":794,"passed_time":0.4627658458,"remaining_time":0.1193295577},
{"learn":[3.349169061],"iteration":795,"passed_time":0.4632239977,"remaining_time":0.1187156979},
{"learn":[3.346211014],"iteration":796,"passed_time":0.4637178703,"remaining_time":0.1181113271},
{"learn":[3.344560452],"iteration":797,"passed_time":0.4641924054,"remaining_time":0.1175023382},
{"learn":[3.344445461],"iteration":798,"passed_time":0.46464844,"remaining_time":0.1168890318},
{"learn":[3.342608898],"iteration":799,"passed_time":0.4651110693,"remaining_time":0.1162777673},
{"learn":[3.339572899],"iteration":800,"passed_time":0.4655725818,"remaining_time":0.1156665965},
{"learn":[3.339309302],"iteration":801,"passed_time":0.4660527499,"remaining_time":0.1150604046},
{"learn":[3.33698088],"iteration":802,"passed_time":0.466628174,"remaining_time":0.1144778957},
{"learn":[3.334746342],"iteration":803,"passed_time":0.4672630356,"remaining_time":0.1139098942},
{"learn":[3.332048511],"iteration":804,"passed_time":0.4678572751,"remaining_time":0.1133318865},
{"learn":[3.331932544],"iteration":805,"passed_time":0.4684457659,"remaining_time":0.1127524548},
{"learn":[3.330541133],"iteration":806,"passed_time":0.4689473775,"remaining_time":0.1121522229},
{"learn":[3.329124989],"iteration":807,"passed_time":0.4695641513,"remaining_time":0.1115796003},
{"learn":[3.32583918],"iteration":808,"passed_time":0.4701232455,"remaining_time":0.1109932508},
{"learn":[3.325287299],"iteration":809,"passed_time":0.4706670207,"remaining_time":0.1104033752},
{"learn":[3.322745162],"iteration":810,"passed_time":0.4711907179,"remaining_time":0.1098089343},
{"learn":[3.319733662],"iteration":811,"passed_time":0.4717048849,"remaining_time":0.109212461},
{"learn":[3.318080007],"iteration":812,"passed_time":0.4722271248,"remaining_time":0.1086180472},
{"learn":[3.317179538],"iteration":813,"passed_time":0.4728302842,"remaining_time":0.1080423008},
{"learn":[3.315685949],"iteration":814,"passed_time":0.4733998393,"remaining_time":0.1074588592},
{"learn":[3.314944576],"iteration":815,"passed_time":0.4742089515,"remaining_time":0.1069294695},
{"learn":[3.312369052],"iteration":816,"passed_time":0.4748036535,"remaining_time":0.1063513691},
{"learn":[3.312321621],"iteration":817,"passed_time":0.4752048714,"remaining_time":0.1057301792},
{"learn":[3.309465776],"iteration":818,"passed_time":0.4757328624,"remaining_time":0.1051375435},
{"learn":[3.308307377],"iteration":819,"passed_time":0.4763136991,"remaining_time":0.1045566657},
{"learn":[3.308076804],"iteration":820,"passed_time":0.4769204111,"remaining_time":0.1039814295},
{"learn":[3.305643326],"iteration":821,"passed_time":0.4776120676,"remaining_time":0.103424511},
{"learn":[3.304154814],"iteration":822,"passed_time":0.4782093244,"remaining_time":0.1028469628},
{"learn":[3.303076321],"iteration":823,"passed_time":0.4788993953,"remaining_time":0.1022891912},
{"learn":[3.301746372],"iteration":824,"passed_time":0.4794975332,"remaining_time":0.101711598},
{"learn":[3.301345455],"iteration":825,"passed_time":0.4801000483,"remaining_time":0.101134877},
{"learn":[3.299181039],"iteration":826,"passed_time":0.4806287798,"remaining_time":0.1005426589},
{"learn":[3.297989357],"iteration":827,"passed_time":0.4812224828,"remaining_time":0.09996409063},
{"learn":[3.294775182],"iteration":828,"passed_time":0.4818392987,"remaining_time":0.09939025341},
{"learn":[3.293840636],"iteration":829,"passed_time":0.4824333371,"remaining_time":0.09881164735},
{"learn":[3.289279397],"iteration":830,"passed_time":0.4830186423,"remaining_time":0.0982312281},
{"learn":[3.286204979],"iteration":831,"passed_time":0.4836494405,"remaining_time":0.09765998317},
{"learn":[3.284833593],"iteration":832,"passed_time":0.4842629907,"remaining_time":0.09708513739},
{"learn":[3.283519914],"iteration":833,"passed_time":0.4848973871,"remaining_time":0.09651434803},
{"learn":[3.282853026],"iteration":834,"passed_time":0.4855906844,"remaining_time":0.09595504543},
{"learn":[3.281944673],"iteration":835,"passed_time":0.4861882702,"remaining_time":0.0953766463},
{"learn":[3.279764865],"iteration":836,"passed_time":0.4867521979,"remaining_time":0.09479164667},
{"learn":[3.277468839],"iteration":837,"passed_time":0.4873023854,"remaining_time":0.0942040411},
{"learn":[3.277124974],"iteration":838,"passed_time":0.4879378717,"remaining_time":0.09363289314},
{"learn":[3.275636037],"iteration":839,"passed_time":0.488538901,"remaining_time":0.09305502877},
{"learn":[3.274413635],"iteration":840,"passed_time":0.4890985233,"remaining_time":0.09246928087},
{"learn":[3.272636087],"iteration":841,"passed_time":0.489658033,"remaining_time":0.09188357389},
{"learn":[3.269644466],"iteration":842,"passed_time":0.4902944577,"remaining_time":0.09131225369},
{"learn":[3.26852083],"iteration":843,"passed_time":0.4908085366,"remaining_time":0.09071816554},
{"learn":[3.267820927],"iteration":844,"passed_time":0.491358166,"remaining_time":0.09013078784},
{"learn":[3.267331099],"iteration":845,"passed_time":0.4918669821,"remaining_time":0.08953607003},
{"learn":[3.267231014],"iteration":846,"passed_time":0.4923964213,"remaining_time":0.08894528035},
{"learn":[3.267158695],"iteration":847,"passed_time":0.4928994915,"remaining_time":0.08834990885},
{"learn":[3.264718705],"iteration":848,"passed_time":0.4934740372,"remaining_time":0.08776746716},
{"learn":[3.261678512],"iteration":849,"passed_time":0.4941235242,"remaining_time":0.08719826898},
{"learn":[3.261368381],"iteration":850,"passed_time":0.4947634337,"remaining_time":0.0866272052},
{"learn":[3.260128799],"iteration":851,"passed_time":0.4953256473,"remaining_time":0.08604248334},
{"learn":[3.258972952],"iteration":852,"passed_time":0.4958261383,"remaining_time":0.0854471774},
{"learn":[3.258724846],"iteration":853,"passed_time":0.4963649064,"remaining_time":0.08485863739},
{"learn":[3.25686724],"iteration":854,"passed_time":0.4969509561,"remaining_time":0.08427823232},
{"learn":[3.255750259],"iteration":855,"passed_time":0.4975133328,"remaining_time":0.08369383168},
{"learn":[3.254915866],"iteration":856,"passed_time":0.4980393648,"remaining_time":0.08310341793},
{"learn":[3.254348625],"iteration":857,"passed_time":0.4986022018,"remaining_time":0.08251924553},
{"learn":[3.253408514],"iteration":858,"passed_time":0.4991608841,"remaining_time":0.08193444081},
{"learn":[3.253291714],"iteration":859,"passed_time":0.4996643438,"remaining_time":0.08134070713},
{"learn":[3.250186342],"iteration":860,"passed_time":0.5002303023,"remaining_time":0.08075727295},
{"learn":[3.249141318],"iteration":861,"passed_time":0.500839521,"remaining_time":0.08018080498},
{"learn":[3.246300388],"iteration":862,"passed_time":0.5015969163,"remaining_time":0.07962778393},
{"learn":[3.245205135],"iteration":863,"passed_time":0.5023991045,"remaining_time":0.07908134053},
{"learn":[3.244403535],"iteration":864,"passed_time":0.5030118858,"remaining_time":0.07850474519},
{"learn":[3.244211781],"iteration":865,"passed_time":0.5035658543,"remaining_time":0.07791896591},
{"learn":[3.242286347],"iteration":866,"passed_time":0.5040788377,"remaining_time":0.0773269728},
{"learn":[3.239606746],"iteration":867,"passed_time":0.5045635913,"remaining_time":0.07673086873},
{"learn":[3.236773361],"iteration":868,"passed_time":0.5050346869,"remaining_time":0.076132962},
{"learn":[3.234552446],"iteration":869,"passed_time":0.50552352,"remaining_time":0.07553799724},
{"learn":[3.233724647],"iteration":870,"passed_time":0.5059873862,"remaining_time":0.07493957843},
{"learn":[3.230851485],"iteration":871,"passed_time":0.5064640013,"remaining_time":0.07434333964},
{"learn":[3.227728941],"iteration":872,"passed_time":0.5069266045,"remaining_time":0.0737453365},
{"learn":[3.225787575],"iteration":873,"passed_time":0.5073745222,"remaining_time":0.07314552608},
{"learn":[3.222797487],"iteration":874,"passed_time":0.5078630484,"remaining_time":0.07255186405},
{"learn":[3.22137014],"iteration":875,"passed_time":0.5083196279,"remaining_time":0.07195391994},
{"learn":[3.219701963],"iteration":876,"passed_time":0.5087790873,"remaining_time":0.07135670209},
{"learn":[3.21783327],"iteration":877,"passed_time":0.5092795706,"remaining_time":0.07076549842},
{"learn":[3.217713355],"iteration":878,"passed_time":0.5097479021,"remaining_time":0.07017007526},
{"learn":[3.217666091],"iteration":879,"passed_time":0.5101900711,"remaining_time":0.06957137333},
{"learn":[3.214962005],"iteration":880,"passed_time":0.5106487118,"remaining_time":0.06897525165},
{"learn":[3.214081828],"iteration":881,"passed_time":0.5111185872,"remaining_time":0.06838094478},
{"learn":[3.213358337],"iteration":882,"passed_time":0.5115833065,"remaining_time":0.06778623654},
{"learn":[3.210850401],"iteration":883,"passed_time":0.5120417713,"remaining_time":0.06719100167},
{"learn":[3.207810328],"iteration":884,"passed_time":0.5125051932,"remaining_time":0.06659672002},
{"learn":[3.204935073],"iteration":885,"passed_time":0.5129780297,"remaining_time":0.06600394513},
{"learn":[3.20280198],"iteration":886,"passed_time":0.5134581253,"remaining_time":0.06541236545},
{"learn":[3.200663495],"iteration":887,"passed_time":0.5139389004,"remaining_time":0.06482112257},
{"learn":[3.197301669],"iteration":888,"passed_time":0.5144031428,"remaining_time":0.06422806395},
{"learn":[3.195666943],"iteration":889,"passed_time":0.5148660538,"remaining_time":0.06363513024},
{"learn":[3.193886506],"iteration":890,"passed_time":0.5154150869,"remaining_time":0.0630530241},
{"learn":[3.190601248],"iteration":891,"passed_time":0.5160253474,"remaining_time":0.06247840529},
{"learn":[3.188983797],"iteration":892,"passed_time":0.5164981106,"remaining_time":0.06188723162},
{"learn":[3.187365749],"iteration":893,"passed_time":0.5169926589,"remaining_time":0.06129890586},
{"learn":[3.186160771],"iteration":894,"passed_time":0.517526807,"remaining_time":0.06071543545},
{"learn":[3.185358981],"iteration":895,"passed_time":0.5180733373,"remaining_time":0.06013351237},
{"learn":[3.183832164],"iteration":896,"passed_time":0.5185484883,"remaining_time":0.0595434719},
{"learn":[3.183106966],"iteration":897,"passed_time":0.5190083191,"remaining_time":0.05895194716},
{"learn":[3.182838152],"iteration":898,"passed_time":0.5194622573,"remaining_time":0.05836005338},
{"learn":[3.180835453],"iteration":899,"passed_time":0.5199344123,"remaining_time":0.05777049025},
{"learn":[3.179957348],"iteration":900,"passed_time":0.5204238957,"remaining_time":0.05718309176},
{"learn":[3.179752966],"iteration":901,"passed_time":0.5208860056,"remaining_time":0.05659293631},
{"learn":[3.178851983],"iteration":902,"passed_time":0.5213510102,"remaining_time":0.0560033754},
{"learn":[3.176748586],"iteration":903,"passed_time":0.5218090876,"remaining_time":0.05541335443},
{"learn":[3.172960988],"iteration":904,"passed_time":0.5222729009,"remaining_time":0.05482422716},
{"learn":[3.172794225],"iteration":905,"passed_time":0.5227253456,"remaining_time":0.05423419701},
{"learn":[3.169996507],"iteration":906,"passed_time":0.523219758,"remaining_time":0.05364877342},
{"learn":[3.16813015],"iteration":907,"passed_time":0.5236823047,"remaining_time":0.05306032162},
{"learn":[3.166920871],"iteration":908,"passed_time":0.5241530877,"remaining_time":0.05247297138},
{"learn":[3.16531606],"iteration":909,"passed_time":0.5246124537,"remaining_time":0.05188474817},
{"learn":[3.162035247],"iteration":910,"passed_time":0.5250884918,"remaining_time":0.05129843663},
{"learn":[3.16189467],"iteration":911,"passed_time":0.5255279349,"remaining_time":0.05070883582},
{"learn":[3.161008416],"iteration":912,"passed_time":0.5260098504,"remaining_time":0.05012361115},
{"learn":[3.160560787],"iteration":913,"passed_time":0.5264565981,"remaining_time":0.04953530354},
{"learn":[3.160416261],"iteration":914,"passed_time":0.5269037709,"remaining_time":0.04894734484},
{"learn":[3.15844291],"iteration":915,"passed_time":0.5273651584,"remaining_time":0.04836099706},
{"learn":[3.155040501],"iteration":916,"passed_time":0.5278246783,"remaining_time":0.04777475278},
{"learn":[3.154937548],"iteration":917,"passed_time":0.5282724818,"remaining_time":0.04718773802},
{"learn":[3.153721161],"iteration":918,"passed_time":0.5287521113,"remaining_time":0.04660383136},
{"learn":[3.153170511],"iteration":919,"passed_time":0.5292054032,"remaining_time":0.04601786115},
{"learn":[3.153113601],"iteration":920,"passed_time":0.5296560977,"remaining_time":0.04543195627},
{"learn":[3.150607379],"iteration":921,"passed_time":0.5301144944,"remaining_time":0.04484699628},
{"learn":[3.148408359],"iteration":922,"passed_time":0.530605087,"remaining_time":0.04426499642},
{"learn":[3.147495728],"iteration":923,"passed_time":0.5310760739,"remaining_time":0.04368158184},
{"learn":[3.146946235],"iteration":924,"passed_time":0.5315308323,"remaining_time":0.04309709451},
{"learn":[3.14472738],"iteration":925,"passed_time":0.5320434908,"remaining_time":0.04251751438},
{"learn":[3.144469477],"iteration":926,"passed_time":0.5325236745,"remaining_time":0.04193552129},
{"learn":[3.142975516],"iteration":927,"passed_time":0.5330225506,"remaining_time":0.04135519789},
{"learn":[3.14079113],"iteration":928,"passed_time":0.5334845832,"remaining_time":0.04077223402},
{"learn":[3.138173032],"iteration":929,"passed_time":0.5339717947,"remaining_time":0.04019142541},
{"learn":[3.136352813],"iteration":930,"passed_time":0.5344668947,"remaining_time":0.0396114025},
{"learn":[3.133735004],"iteration":931,"passed_time":0.5349211598,"remaining_time":0.03902858247},
{"learn":[3.1319496],"iteration":932,"passed_time":0.5353803787,"remaining_time":0.03844639376},
{"learn":[3.129865343],"iteration":933,"passed_time":0.5358629241,"remaining_time":0.03786611669},
{"learn":[3.129830206],"iteration":934,"passed_time":0.5362041103,"remaining_time":0.03727622157},
{"learn":[3.126676562],"iteration":935,"passed_time":0.5366504702,"remaining_time":0.03669404924},
{"learn":[3.12645665],"iteration":936,"passed_time":0.537117386,"remaining_time":0.0361135489},
{"learn":[3.126378007],"iteration":937,"passed_time":0.5375645965,"remaining_time":0.03553198826},
{"learn":[3.124621914],"iteration":938,"passed_time":0.5380272118,"remaining_time":0.0349517145},
{"learn":[3.123379018],"iteration":939,"passed_time":0.5384957741,"remaining_time":0.03437207069},
{"learn":[3.123332451],"iteration":940,"passed_time":0.5389505978,"remaining_time":0.03379180156},
{"learn":[3.122432444],"iteration":941,"passed_time":0.539404746,"remaining_time":0.03321175718},
{"learn":[3.121889006],"iteration":942,"passed_time":0.5398666131,"remaining_time":0.03263244639},
{"learn":[3.121070914],"iteration":943,"passed_time":0.5403148946,"remaining_time":0.0320525785},
{"learn":[3.118444705],"iteration":944,"passed_time":0.5407856524,"remaining_time":0.03147429723},
{"learn":[3.116820458],"iteration":945,"passed_time":0.5412795643,"remaining_time":0.03089756498},
{"learn":[3.114971041],"iteration":946,"passed_time":0.5417416642,"remaining_time":0.03031922725},
{"learn":[3.114685138],"iteration":947,"passed_time":0.5422006844,"remaining_time":0.02974096581},
{"learn":[3.113399363],"iteration":948,"passed_time":0.5426589746,"remaining_time":0.02916291644},
{"learn":[3.110575399],"iteration":949,"passed_time":0.5431388137,"remaining_time":0.02858625335},
{"learn":[3.110466553],"iteration":950,"passed_time":0.5435981828,"remaining_time":0.02800873918},
{"learn":[3.108691641],"iteration":951,"passed_time":0.5440500967,"remaining_time":0.02743109731},
{"learn":[3.107898017],"iteration":952,"passed_time":0.5445104512,"remaining_time":0.02685413558},
{"learn":[3.105551729],"iteration":953,"passed_time":0.5449715771,"remaining_time":0.0262774555},
{"learn":[3.104824945],"iteration":954,"passed_time":0.5454238263,"remaining_time":0.02570059915},
{"learn":[3.103186704],"iteration":955,"passed_time":0.5458851757,"remaining_time":0.02512442231},
{"learn":[3.102330655],"iteration":956,"passed_time":0.5464137514,"remaining_time":0.02455150607},
{"learn":[3.102291298],"iteration":957,"passed_time":0.5469177636,"remaining_time":0.0239776055},
{"learn":[3.100363529],"iteration":958,"passed_time":0.5473784891,"remaining_time":0.02340200006},
{"learn":[3.097871596],"iteration":959,"passed_time":0.5478427192,"remaining_time":0.02282677997},
{"learn":[3.097372213],"iteration":960,"passed_time":0.548322539,"remaining_time":0.02225242354},
{"learn":[3.095981813],"iteration":961,"passed_time":0.5487767962,"remaining_time":0.0216772539},
{"learn":[3.095347452],"iteration":962,"passed_time":0.5492601538,"remaining_time":0.02110345347},
{"learn":[3.094728409],"iteration":963,"passed_time":0.5497194048,"remaining_time":0.02052894043},
{"learn":[3.094118537],"iteration":964,"passed_time":0.5502110816,"remaining_time":0.01995584234},
{"learn":[3.093793695],"iteration":965,"passed_time":0.5506529088,"remaining_time":0.01938115828},
{"learn":[3.092581602],"iteration":966,"passed_time":0.5511316624,"remaining_time":0.01880800916},
{"learn":[3.091694202],"iteration":967,"passed_time":0.5515948133,"remaining_time":0.01823453928},
{"learn":[3.090298312],"iteration":968,"passed_time":0.5520726574,"remaining_time":0.01766176716},
{"learn":[3.090020107],"iteration":969,"passed_time":0.5525248641,"remaining_time":0.01708839786},
{"learn":[3.088949869],"iteration":970,"passed_time":0.5529767399,"remaining_time":0.01651526824},
{"learn":[3.086700204],"iteration":971,"passed_time":0.5534270062,"remaining_time":0.01594234174},
{"learn":[3.086584317],"iteration":972,"passed_time":0.5538788519,"remaining_time":0.0153697112},
{"learn":[3.084850742],"iteration":973,"passed_time":0.5543292055,"remaining_time":0.01479728885},
{"learn":[3.084239948],"iteration":974,"passed_time":0.5547854721,"remaining_time":0.01422526851},
{"learn":[3.082561673],"iteration":975,"passed_time":0.555251742,"remaining_time":0.01365373136},
{"learn":[3.07991814],"iteration":976,"passed_time":0.5557414883,"remaining_time":0.01308296237},
{"learn":[3.079350277],"iteration":977,"passed_time":0.5561909728,"remaining_time":0.01251145338},
{"learn":[3.077637462],"iteration":978,"passed_time":0.5566432432,"remaining_time":0.01194025343},
{"learn":[3.076733301],"iteration":979,"passed_time":0.5571043835,"remaining_time":0.01136947721},
{"learn":[3.07594065],"iteration":980,"passed_time":0.5575561623,"remaining_time":0.01079874321},
{"learn":[3.072594655],"iteration":981,"passed_time":0.5580346767,"remaining_time":0.01022874153},
{"learn":[3.071977674],"iteration":982,"passed_time":0.5584915396,"remaining_time":0.009658551549},
{"learn":[3.069532634],"iteration":983,"passed_time":0.5589524563,"remaining_time":0.009088657826},
{"learn":[3.068870784],"iteration":984,"passed_time":0.5594053326,"remaining_time":0.008518862933},
{"learn":[3.068801463],"iteration":985,"passed_time":0.5598367577,"remaining_time":0.007949000617},
{"learn":[3.067433249],"iteration":986,"passed_time":0.560340219,"remaining_time":0.007380367626},
{"learn":[3.065611456],"iteration":987,"passed_time":0.5608497432,"remaining_time":0.006811940201},
{"learn":[3.063039162],"iteration":988,"passed_time":0.5613471043,"remaining_time":0.00624349661},
{"learn":[3.06177873],"iteration":989,"passed_time":0.5618203852,"remaining_time":0.005674953386},
{"learn":[3.061689148],"iteration":990,"passed_time":0.5622696589,"remaining_time":0.00510638439},
{"learn":[3.058984039],"iteration":991,"passed_time":0.5627267169,"remaining_time":0.004538118685},
{"learn":[3.057492984],"iteration":992,"passed_time":0.56317821,"remaining_time":0.003970037734},
{"learn":[3.057290731],"iteration":993,"passed_time":0.5636278295,"remaining_time":0.003402180057},
{"learn":[3.056068348],"iteration":994,"passed_time":0.5640801473,"remaining_time":0.002834573604},
{"learn":[3.054987307],"iteration":995,"passed_time":0.5646457507,"remaining_time":0.002267653617},
{"learn":[3.054200234],"iteration":996,"passed_time":0.5652100327,"remaining_time":0.001700732295},
{"learn":[3.052732869],"iteration":997,"passed_time":0.5658083529,"remaining_time":0.001133884475},
{"learn":[3.051787862],"iteration":998,"passed_time":0.5663133949,"remaining_time":0.0005668802752},
{"learn":[3.051366222],"iteration":999,"passed_time":0.5667677554,"remaining_time":0}
]}